{"data": [{"text": "@Nicole_H31 Hello Nicole,\nplease provide us the claim file number via DM in order to verify. Thank you.", "source": "Qualtrics Social Connect", "id": "1587111368381054976", "entities": {"annotations": [{"start": 18, "end": 23, "probability": 0.5682, "type": "Person", "normalized_text": "Nicole"}], "mentions": [{"start": 0, "end": 11, "username": "Nicole_H31", "id": "32544131"}]}, "lang": "en", "in_reply_to_user_id": "32544131", "created_at": "2022-10-31T15:56:51.000Z", "edit_history_tweet_ids": ["1587111368381054976"], "conversation_id": "1587092852789616642", "author_id": "107472906", "public_metrics": {"retweet_count": 0, "reply_count": 0, "like_count": 0, "quote_count": 0}}, {"text": "@vsalles_ Hello Vanessa,\nwe have replied via DM. Thank you.", "source": "Qualtrics Social Connect", "id": "1587110390076432386", "entities": {"annotations": [{"start": 16, "end": 22, "probability": 0.5972, "type": "Other", "normalized_text": "Vanessa"}], "mentions": [{"start": 0, "end": 9, "username": "vsalles_", "id": "64900929"}]}, "lang": "en", "in_reply_to_user_id": "64900929", "created_at": "2022-10-31T15:52:58.000Z", "edit_history_tweet_ids": ["1587110390076432386"], "conversation_id": "1587091654804213761", "author_id": "107472906", "public_metrics": {"retweet_count": 0, "reply_count": 0, "like_count": 0, "quote_count": 0}}, {"text": "@NikkiChagra @nikkichagra Hello Nicole, thank you for your feedback. If you have additional questions, please let us know.", "source": "Qualtrics Social Connect", "id": "1587102778719178752", "entities": {"annotations": [{"start": 32, "end": 37, "probability": 0.5621, "type": "Person", "normalized_text": "Nicole"}], "mentions": [{"start": 0, "end": 12, "username": "NikkiChagra", "id": "1423990612802609159"}, {"start": 13, "end": 25, "username": "NikkiChagra", "id": "1423990612802609159"}]}, "lang": "en", "in_reply_to_user_id": "1423990612802609159", "created_at": "2022-10-31T15:22:44.000Z", "edit_history_tweet_ids": ["1587102778719178752"], "conversation_id": "1586929897347358720", "author_id": "107472906", "public_metrics": {"retweet_count": 0, "reply_count": 0, "like_count": 0, "quote_count": 0}}, {"text": "@Legumendoas @legumendoas Ol\u00e1, informamos que poder\u00e1 consultar a lista de refei\u00e7\u00f5es especiais dispon\u00edveis aqui: https://t.co/ar8WUNFaGT\nObrigado.", "source": "Qualtrics Social Connect", "id": "1587102507469361152", "lang": "pt", "in_reply_to_user_id": "1236791282929991681", "created_at": "2022-10-31T15:21:39.000Z", "edit_history_tweet_ids": ["1587102507469361152"], "conversation_id": "1587090149099307008", "author_id": "107472906", "entities": {"urls": [{"start": 112, "end": 135, "url": "https://t.co/ar8WUNFaGT", "expanded_url": "https://www.flytap.com/pt-pt/a-bordo/refeicoes-a-bordo/refeicoes-especiais?accordionid=1", "display_url": "flytap.com/pt-pt/a-bordo/\u2026", "images": [{"url": "https://pbs.twimg.com/news_img/1587102518810664962/iowyvc-c?format=jpg&name=orig", "width": 511, "height": 201}, {"url": "https://pbs.twimg.com/news_img/1587102518810664962/iowyvc-c?format=jpg&name=150x150", "width": 150, "height": 150}], "status": 200, "title": "Refei\u00e7\u00f5es especiais | TAP Air Portugal", "description": "Conhe\u00e7a as refei\u00e7\u00f5es especialmente feitas para si", "unwound_url": "https://www.flytap.com/pt-pt/a-bordo/refeicoes-a-bordo/refeicoes-especiais?accordionid=1"}], "mentions": [{"start": 0, "end": 12, "username": "Legumendoas", "id": "1236791282929991681"}, {"start": 13, "end": 25, "username": "Legumendoas", "id": "1236791282929991681"}]}, "public_metrics": {"retweet_count": 0, "reply_count": 1, "like_count": 0, "quote_count": 0}}, {"text": "@cedraz_diego Ol\u00e1, respondemos por mensagem privada. Obrigado.", "source": "Qualtrics Social Connect", "id": "1587100627653595137", "lang": "pt", "in_reply_to_user_id": "1468451477392076806", "created_at": "2022-10-31T15:14:11.000Z", "edit_history_tweet_ids": ["1587100627653595137"], "conversation_id": "1587044967129747457", "author_id": "107472906", "public_metrics": {"retweet_count": 0, "reply_count": 1, "like_count": 0, "quote_count": 0}, "entities": {"mentions": [{"start": 0, "end": 13, "username": "cedraz_diego", "id": "1468451477392076806"}]}}, {"text": "@Ellesmama1 @ellesmama1 Hello Ellesmama, can you provide us with a screenshot of the e-mail you've received by direct message, so that it can be verified?\nThank you.", "source": "Qualtrics Social Connect", "id": "1587099905994137604", "entities": {"annotations": [{"start": 30, "end": 38, "probability": 0.7978, "type": "Other", "normalized_text": "Ellesmama"}], "mentions": [{"start": 0, "end": 11, "username": "Ellesmama1", "id": "1449854727920013319"}, {"start": 12, "end": 23, "username": "Ellesmama1", "id": "1449854727920013319"}]}, "lang": "en", "in_reply_to_user_id": "1449854727920013319", "created_at": "2022-10-31T15:11:19.000Z", "edit_history_tweet_ids": ["1587099905994137604"], "conversation_id": "1587088750936481794", "author_id": "107472906", "public_metrics": {"retweet_count": 0, "reply_count": 0, "like_count": 0, "quote_count": 0}}, {"text": "@acruzarelcharco @NauticoNET1998 Se continuar sem conseguir concluir a sua passagem, pedimos que nos envie, por mensagem privada, um print screen do constrangimento e os dados da sua reserva. Disponha se necessitar de ajuda adicional. Obrigado. (II/II)", "source": "Qualtrics Social Connect", "id": "1587099636090691585", "lang": "pt", "in_reply_to_user_id": "1572346755999571971", "created_at": "2022-10-31T15:10:14.000Z", "edit_history_tweet_ids": ["1587099636090691585"], "conversation_id": "1587087426496913409", "author_id": "107472906", "public_metrics": {"retweet_count": 0, "reply_count": 0, "like_count": 0, "quote_count": 0}, "entities": {"mentions": [{"start": 0, "end": 16, "username": "acruzarelcharco", "id": "1572346755999571971"}, {"start": 17, "end": 32, "username": "NauticoNET1998", "id": "94226444"}]}}, {"text": "@acruzarelcharco @NauticoNET1998 Ol\u00e1, lamentamos imenso a situa\u00e7\u00e3o e todos os constrangimentos causados. De forma a efetuar a sua reserva, solicitamos que limpe os cookies do seu browser e tente novamente atrav\u00e9s do Google Chrome. (I/II)", "source": "Qualtrics Social Connect", "id": "1587099626859122690", "context_annotations": [{"domain": {"id": "30", "name": "Entities [Entity Service]", "description": "Entity Service top level domain, every item that is in Entity Service should be in this domain"}, "entity": {"id": "781974596752842752", "name": "Services"}}, {"domain": {"id": "47", "name": "Brand", "description": "Brands and Companies"}, "entity": {"id": "10026378521", "name": "Google "}}, {"domain": {"id": "48", "name": "Product", "description": "Products created by Brands.  Examples: Ford Explorer, Apple iPhone."}, "entity": {"id": "10052778493", "name": "Google Chrome", "description": "Google Chrome"}}, {"domain": {"id": "48", "name": "Product", "description": "Products created by Brands.  Examples: Ford Explorer, Apple iPhone."}, "entity": {"id": "1395474411180892160", "name": "Google brand conversation"}}, {"domain": {"id": "131", "name": "Unified Twitter Taxonomy", "description": "A taxonomy of user interests. "}, "entity": {"id": "10026378521", "name": "Google "}}], "entities": {"annotations": [{"start": 216, "end": 228, "probability": 0.7421, "type": "Other", "normalized_text": "Google Chrome"}], "mentions": [{"start": 0, "end": 16, "username": "acruzarelcharco", "id": "1572346755999571971"}, {"start": 17, "end": 32, "username": "NauticoNET1998", "id": "94226444"}]}, "lang": "pt", "in_reply_to_user_id": "1572346755999571971", "created_at": "2022-10-31T15:10:12.000Z", "edit_history_tweet_ids": ["1587099626859122690"], "conversation_id": "1587087426496913409", "author_id": "107472906", "public_metrics": {"retweet_count": 0, "reply_count": 0, "like_count": 0, "quote_count": 0}}, {"text": "@saninemoreira @saninemoreira Hello Sanine, we are sorry for the inconvenience. If we can help with some question through this channel, please provide with your booking code. For security reasons, we suggest that you send it by direct message. \nThank you.", "source": "Qualtrics Social Connect", "id": "1587098241396613123", "entities": {"annotations": [{"start": 36, "end": 41, "probability": 0.6894, "type": "Other", "normalized_text": "Sanine"}], "mentions": [{"start": 0, "end": 14, "username": "saninemoreira", "id": "215653906"}, {"start": 15, "end": 29, "username": "saninemoreira", "id": "215653906"}]}, "lang": "en", "in_reply_to_user_id": "215653906", "created_at": "2022-10-31T15:04:42.000Z", "edit_history_tweet_ids": ["1587098241396613123"], "conversation_id": "1587080441596633095", "author_id": "107472906", "public_metrics": {"retweet_count": 0, "reply_count": 0, "like_count": 0, "quote_count": 0}}, {"text": "@HevMM01 @hevmm01Hello Heather, we replied to your direct messages. Thank you.", "source": "Qualtrics Social Connect", "id": "1587095992373071873", "entities": {"annotations": [{"start": 23, "end": 29, "probability": 0.6538, "type": "Other", "normalized_text": "Heather"}], "mentions": [{"start": 0, "end": 8, "username": "HevMM01", "id": "729907646577381376"}]}, "lang": "en", "in_reply_to_user_id": "729907646577381376", "created_at": "2022-10-31T14:55:46.000Z", "edit_history_tweet_ids": ["1587095992373071873"], "conversation_id": "1583038479990038528", "author_id": "107472906", "public_metrics": {"retweet_count": 0, "reply_count": 0, "like_count": 0, "quote_count": 0}}, {"text": "@2MonkeysTravel Hello Kach, your request is being processed and it will be finalized as soon as possible. If you have any other questions we can help you with, feel free to contact us. Thank you.", "source": "Qualtrics Social Connect", "id": "1587090764642893824", "context_annotations": [{"domain": {"id": "46", "name": "Business Taxonomy", "description": "Categories within Brand Verticals that narrow down the scope of Brands"}, "entity": {"id": "1557697439489880065", "name": "Travel & Transportation Business", "description": "Brands, companies, advertisers and every non-person handle with the profit intent related to travel as airlines, travel agencies, hotels"}}, {"domain": {"id": "30", "name": "Entities [Entity Service]", "description": "Entity Service top level domain, every item that is in Entity Service should be in this domain"}, "entity": {"id": "839159814991167489", "name": "Travel", "description": "Travel"}}, {"domain": {"id": "66", "name": "Interests and Hobbies Category", "description": "A grouping of interests and hobbies entities, like Novelty Food or Destinations"}, "entity": {"id": "842061030951809024", "name": "Travel novelty", "description": "Travel novelty"}}, {"domain": {"id": "67", "name": "Interests and Hobbies", "description": "Interests, opinions, and behaviors of individuals, groups, or cultures; like Speciality Cooking or Theme Parks"}, "entity": {"id": "842066429474033665", "name": "Travel Blogs", "description": "This entity includes Tweets @ and from ~175 travel blog handles."}}], "entities": {"annotations": [{"start": 22, "end": 25, "probability": 0.6537, "type": "Other", "normalized_text": "Kach"}], "mentions": [{"start": 0, "end": 15, "username": "2MonkeysTravel", "id": "2824792399"}]}, "lang": "en", "in_reply_to_user_id": "2824792399", "created_at": "2022-10-31T14:34:59.000Z", "edit_history_tweet_ids": ["1587090764642893824"], "conversation_id": "1587084829690310656", "author_id": "107472906", "public_metrics": {"retweet_count": 0, "reply_count": 1, "like_count": 0, "quote_count": 0}}, {"text": "@Run_itt Hello Dr. Ronit yarden, as informed via DM, we are verifying your situation and you will be contacted via email as soon as possible. Thank you.", "source": "Qualtrics Social Connect", "id": "1587088466315296770", "entities": {"annotations": [{"start": 19, "end": 30, "probability": 0.7312, "type": "Other", "normalized_text": "Ronit yarden"}], "mentions": [{"start": 0, "end": 8, "username": "Run_itt", "id": "3096799408"}]}, "lang": "en", "in_reply_to_user_id": "3096799408", "created_at": "2022-10-31T14:25:51.000Z", "edit_history_tweet_ids": ["1587088466315296770"], "conversation_id": "1586759652796243976", "author_id": "107472906", "public_metrics": {"retweet_count": 0, "reply_count": 0, "like_count": 0, "quote_count": 0}}, {"text": "@diegojatem @IATA Let us know if we can be of further assistance. Thank you. (II/II)", "source": "Qualtrics Social Connect", "id": "1587074962065596416", "context_annotations": [{"domain": {"id": "45", "name": "Brand Vertical", "description": "Top level entities that describe a Brands industry"}, "entity": {"id": "781974596157251587", "name": "Government/Education"}}, {"domain": {"id": "30", "name": "Entities [Entity Service]", "description": "Entity Service top level domain, every item that is in Entity Service should be in this domain"}, "entity": {"id": "781974597226729473", "name": "Non-profit - Government/Education"}}, {"domain": {"id": "47", "name": "Brand", "description": "Brands and Companies"}, "entity": {"id": "10048460338", "name": "International Air Transport Association", "description": "International Air Transport Association"}}], "lang": "en", "in_reply_to_user_id": "252246576", "created_at": "2022-10-31T13:32:12.000Z", "edit_history_tweet_ids": ["1587074962065596416"], "conversation_id": "1587045201574596608", "author_id": "107472906", "public_metrics": {"retweet_count": 0, "reply_count": 1, "like_count": 0, "quote_count": 0}, "entities": {"mentions": [{"start": 0, "end": 11, "username": "diegojatem", "id": "252246576"}, {"start": 12, "end": 17, "username": "IATA", "id": "27067896"}]}}, {"text": "@diegojatem @IATA Hello Diego, we have verified that you have already been contacted regarding your file. At the moment, we kindly request you to reply to the last email received without changing its body. In the meantime, we have reinforced the analysis of the situation. (I/II)", "source": "Qualtrics Social Connect", "id": "1587074946777358336", "context_annotations": [{"domain": {"id": "45", "name": "Brand Vertical", "description": "Top level entities that describe a Brands industry"}, "entity": {"id": "781974596157251587", "name": "Government/Education"}}, {"domain": {"id": "30", "name": "Entities [Entity Service]", "description": "Entity Service top level domain, every item that is in Entity Service should be in this domain"}, "entity": {"id": "781974597226729473", "name": "Non-profit - Government/Education"}}, {"domain": {"id": "47", "name": "Brand", "description": "Brands and Companies"}, "entity": {"id": "10048460338", "name": "International Air Transport Association", "description": "International Air Transport Association"}}], "entities": {"annotations": [{"start": 24, "end": 28, "probability": 0.5515, "type": "Person", "normalized_text": "Diego"}], "mentions": [{"start": 0, "end": 11, "username": "diegojatem", "id": "252246576"}, {"start": 12, "end": 17, "username": "IATA", "id": "27067896"}]}, "lang": "en", "in_reply_to_user_id": "252246576", "created_at": "2022-10-31T13:32:08.000Z", "edit_history_tweet_ids": ["1587074946777358336"], "conversation_id": "1587045201574596608", "author_id": "107472906", "public_metrics": {"retweet_count": 0, "reply_count": 1, "like_count": 0, "quote_count": 0}}, {"text": "@ArisDama @ArisDama Ol\u00e1 Aris,\nInformamos que respondemos \u00e0 sua mensagem privada. Obrigada.", "source": "Qualtrics Social Connect", "id": "1587066036687446019", "entities": {"annotations": [{"start": 24, "end": 27, "probability": 0.5985, "type": "Other", "normalized_text": "Aris"}], "mentions": [{"start": 0, "end": 9, "username": "ArisDama", "id": "58855024"}, {"start": 10, "end": 19, "username": "ArisDama", "id": "58855024"}]}, "lang": "pt", "in_reply_to_user_id": "58855024", "created_at": "2022-10-31T12:56:44.000Z", "edit_history_tweet_ids": ["1587066036687446019"], "conversation_id": "1586979787343544320", "author_id": "107472906", "public_metrics": {"retweet_count": 0, "reply_count": 0, "like_count": 0, "quote_count": 0}}, {"text": "@roy_mccaw @roy_mccaw Hello Roy, we replied by direct message. Thank you.", "source": "Qualtrics Social Connect", "id": "1587060255212576769", "entities": {"annotations": [{"start": 28, "end": 30, "probability": 0.542, "type": "Person", "normalized_text": "Roy"}], "mentions": [{"start": 0, "end": 10, "username": "roy_mccaw", "id": "1425360932386054146"}, {"start": 11, "end": 21, "username": "roy_mccaw", "id": "1425360932386054146"}]}, "lang": "en", "in_reply_to_user_id": "1425360932386054146", "created_at": "2022-10-31T12:33:45.000Z", "edit_history_tweet_ids": ["1587060255212576769"], "conversation_id": "1587045201574596608", "author_id": "107472906", "public_metrics": {"retweet_count": 0, "reply_count": 2, "like_count": 1, "quote_count": 0}}, {"text": "@GiuseppePeltron @giuseppepeltron Hello Giuseppe, we replied to your direct message. Thank you.", "source": "Qualtrics Social Connect", "id": "1587058843191836674", "entities": {"annotations": [{"start": 40, "end": 47, "probability": 0.5542, "type": "Person", "normalized_text": "Giuseppe"}], "mentions": [{"start": 0, "end": 16, "username": "GiuseppePeltron", "id": "791736167213432832"}, {"start": 17, "end": 33, "username": "GiuseppePeltron", "id": "791736167213432832"}]}, "lang": "en", "in_reply_to_user_id": "791736167213432832", "created_at": "2022-10-31T12:28:09.000Z", "edit_history_tweet_ids": ["1587058843191836674"], "conversation_id": "1587050149695684608", "author_id": "107472906", "public_metrics": {"retweet_count": 0, "reply_count": 0, "like_count": 0, "quote_count": 0}}, {"text": "@emtamfabulous Hello Emily,\nWe suggest that you reply to the last email you received on this subject in order to clarify your questions. If you have already done so, you will then receive an email about this matter.\nThank you", "source": "Qualtrics Social Connect", "id": "1587055288322068485", "entities": {"annotations": [{"start": 21, "end": 25, "probability": 0.5053, "type": "Person", "normalized_text": "Emily"}], "mentions": [{"start": 0, "end": 14, "username": "emtamfabulous", "id": "80430427"}]}, "lang": "en", "in_reply_to_user_id": "80430427", "created_at": "2022-10-31T12:14:01.000Z", "edit_history_tweet_ids": ["1587055288322068485"], "conversation_id": "1587047862780792832", "author_id": "107472906", "public_metrics": {"retweet_count": 0, "reply_count": 4, "like_count": 0, "quote_count": 0}}, {"text": "@Wasim571 Hello Wasim,\nwe have replied via DM. Thank you.", "source": "Qualtrics Social Connect", "id": "1587052440523866114", "entities": {"annotations": [{"start": 16, "end": 20, "probability": 0.4675, "type": "Person", "normalized_text": "Wasim"}], "mentions": [{"start": 0, "end": 9, "username": "Wasim571", "id": "125065841"}]}, "lang": "en", "in_reply_to_user_id": "125065841", "created_at": "2022-10-31T12:02:42.000Z", "edit_history_tweet_ids": ["1587052440523866114"], "conversation_id": "1585265584207544321", "author_id": "107472906", "public_metrics": {"retweet_count": 0, "reply_count": 0, "like_count": 0, "quote_count": 0}}, {"text": "@mocosta3 Hello morgan,\nwe have replied via DM. Thank you.", "source": "Qualtrics Social Connect", "id": "1587051880357761025", "entities": {"annotations": [{"start": 16, "end": 21, "probability": 0.4521, "type": "Other", "normalized_text": "morgan"}], "mentions": [{"start": 0, "end": 9, "username": "mocosta3", "id": "2821628915"}]}, "lang": "en", "in_reply_to_user_id": "2821628915", "created_at": "2022-10-31T12:00:28.000Z", "edit_history_tweet_ids": ["1587051880357761025"], "conversation_id": "1585191420021080064", "author_id": "107472906", "public_metrics": {"retweet_count": 0, "reply_count": 0, "like_count": 0, "quote_count": 0}}, {"text": "@la_taupe123 @TAP_Portugal Bonjour Leo,\nAfin de v\u00e9rifier votre situation, veuillez nous indiquer votre num\u00e9ro de dossier par DM.\nMerci.", "source": "Qualtrics Social Connect", "id": "1587051424399212545", "lang": "fr", "in_reply_to_user_id": "131241408", "created_at": "2022-10-31T11:58:40.000Z", "edit_history_tweet_ids": ["1587051424399212545"], "conversation_id": "1587045256276705282", "author_id": "107472906", "public_metrics": {"retweet_count": 0, "reply_count": 1, "like_count": 0, "quote_count": 0}, "entities": {"mentions": [{"start": 0, "end": 12, "username": "la_taupe123", "id": "131241408"}, {"start": 13, "end": 26, "username": "TAP_Portugal", "id": "68679960"}]}}, {"text": "@mikesyard Hello Mike, we replied to your direct message. Thank you.", "source": "Qualtrics Social Connect", "id": "1587050797770088448", "entities": {"annotations": [{"start": 17, "end": 20, "probability": 0.5996, "type": "Person", "normalized_text": "Mike"}], "mentions": [{"start": 0, "end": 10, "username": "mikesyard", "id": "59655069"}]}, "lang": "en", "in_reply_to_user_id": "59655069", "created_at": "2022-10-31T11:56:10.000Z", "edit_history_tweet_ids": ["1587050797770088448"], "conversation_id": "1587014569955889152", "author_id": "107472906", "public_metrics": {"retweet_count": 0, "reply_count": 0, "like_count": 0, "quote_count": 0}}, {"text": "@Nicolas1Leger Bonjour L\u00c9GER, nous sommes d\u00e9sol\u00e9s pour la g\u00eane occasionn\u00e9e, si vous avez encore besoin d'assistance, veuillez nous contacter par message priv\u00e9 avec les d\u00e9tails de votre r\u00e9servation. Merci.", "source": "Qualtrics Social Connect", "id": "1587048688395984897", "lang": "fr", "in_reply_to_user_id": "1141634260744454144", "created_at": "2022-10-31T11:47:47.000Z", "edit_history_tweet_ids": ["1587048688395984897"], "conversation_id": "1586875993511403521", "author_id": "107472906", "public_metrics": {"retweet_count": 0, "reply_count": 0, "like_count": 0, "quote_count": 0}, "entities": {"mentions": [{"start": 0, "end": 14, "username": "Nicolas1Leger", "id": "1141634260744454144"}]}}, {"text": "This Halloween, meet the scariest side of our destinations. \ud83d\udc7b\nFrom sinister to creepy, can you make it to the maximum level? Good luck to the bravest ones! \ud83c\udf83\nBook your trip now and get to know all these places up close in https://t.co/ihLfQ3U2ki. https://t.co/JreXEiPPSC", "source": "Twitter Web App", "id": "1587045201574596608", "context_annotations": [{"domain": {"id": "29", "name": "Events [Entity Service]", "description": "Real world events. "}, "entity": {"id": "1301463450099482625", "name": "Halloween ", "description": "This entity includes all conversations for Halloween for all years"}}, {"domain": {"id": "46", "name": "Business Taxonomy", "description": "Categories within Brand Verticals that narrow down the scope of Brands"}, "entity": {"id": "1557696940178935808", "name": "Gaming Business", "description": "Brands, companies, advertisers and every non-person handle with the profit intent related to offline and online games such as gaming consoles, tabletop games, video game publishers"}}, {"domain": {"id": "131", "name": "Unified Twitter Taxonomy", "description": "A taxonomy of user interests. "}, "entity": {"id": "1291095284756357120", "name": "Cultural events"}}, {"domain": {"id": "131", "name": "Unified Twitter Taxonomy", "description": "A taxonomy of user interests. "}, "entity": {"id": "1296394094009151488", "name": "Halloween"}}, {"domain": {"id": "131", "name": "Unified Twitter Taxonomy", "description": "A taxonomy of user interests. "}, "entity": {"id": "1436053202835689485", "name": "Events"}}], "entities": {"annotations": [{"start": 5, "end": 13, "probability": 0.8093, "type": "Other", "normalized_text": "Halloween"}], "urls": [{"start": 222, "end": 245, "url": "https://t.co/ihLfQ3U2ki", "expanded_url": "http://flytap.com/flights-tw", "display_url": "flytap.com/flights-tw", "images": [{"url": "https://pbs.twimg.com/news_img/1594741829697929216/p2WXyl9A?format=jpg&name=orig", "width": 700, "height": 255}, {"url": "https://pbs.twimg.com/news_img/1594741829697929216/p2WXyl9A?format=jpg&name=150x150", "width": 150, "height": 150}], "status": 200, "title": "Find Cheap Flights and Deals: Compare & Book | TAP Air Portugal", "description": "Find cheap flights to 80+ destinations in Europe, Africa and the Americas. Compare great offers on Tap flights and enjoy flying with a premiere airline.", "unwound_url": "https://www.flytap.com/en_us/?utm_source=twitter.com&utm_medium=SOCIAL&utm_campaign=BESTOFFERS&utm_content=ORG&anetwork=SOCIAL"}, {"start": 247, "end": 270, "url": "https://t.co/JreXEiPPSC", "expanded_url": "https://twitter.com/tapairportugal/status/1587045201574596608/photo/1", "display_url": "pic.twitter.com/JreXEiPPSC", "media_key": "3_1587045126941073408"}, {"start": 247, "end": 270, "url": "https://t.co/JreXEiPPSC", "expanded_url": "https://twitter.com/tapairportugal/status/1587045201574596608/photo/1", "display_url": "pic.twitter.com/JreXEiPPSC", "media_key": "3_1587045127100502016"}, {"start": 247, "end": 270, "url": "https://t.co/JreXEiPPSC", "expanded_url": "https://twitter.com/tapairportugal/status/1587045201574596608/photo/1", "display_url": "pic.twitter.com/JreXEiPPSC", "media_key": "3_1587045127247331329"}, {"start": 247, "end": 270, "url": "https://t.co/JreXEiPPSC", "expanded_url": "https://twitter.com/tapairportugal/status/1587045201574596608/photo/1", "display_url": "pic.twitter.com/JreXEiPPSC", "media_key": "3_1587045127431880706"}]}, "lang": "en", "created_at": "2022-10-31T11:33:56.000Z", "edit_history_tweet_ids": ["1587045201574596608"], "conversation_id": "1587045201574596608", "author_id": "107472906", "public_metrics": {"retweet_count": 2, "reply_count": 24, "like_count": 13, "quote_count": 0}}, {"text": "Este Halloween, conhe\u00e7am o lado mais assustador dos nossos destinos. \ud83d\udc7b\nDe sinistro a arrepiante, conseguem chegar ao n\u00edvel m\u00e1ximo? Boa sorte para os mais corajosos! \ud83c\udf83\nReservem j\u00e1 a vossa viagem e conhe\u00e7am de perto todos estes locais em https://t.co/ihLfQ3U2ki. https://t.co/I0QrwRyRBR", "source": "Twitter Web App", "id": "1587044967129747457", "context_annotations": [{"domain": {"id": "29", "name": "Events [Entity Service]", "description": "Real world events. "}, "entity": {"id": "1301463450099482625", "name": "Halloween ", "description": "This entity includes all conversations for Halloween for all years"}}, {"domain": {"id": "46", "name": "Business Taxonomy", "description": "Categories within Brand Verticals that narrow down the scope of Brands"}, "entity": {"id": "1557696940178935808", "name": "Gaming Business", "description": "Brands, companies, advertisers and every non-person handle with the profit intent related to offline and online games such as gaming consoles, tabletop games, video game publishers"}}, {"domain": {"id": "131", "name": "Unified Twitter Taxonomy", "description": "A taxonomy of user interests. "}, "entity": {"id": "1291095284756357120", "name": "Cultural events"}}, {"domain": {"id": "131", "name": "Unified Twitter Taxonomy", "description": "A taxonomy of user interests. "}, "entity": {"id": "1296394094009151488", "name": "Halloween"}}, {"domain": {"id": "131", "name": "Unified Twitter Taxonomy", "description": "A taxonomy of user interests. "}, "entity": {"id": "1436053202835689485", "name": "Events"}}], "entities": {"annotations": [{"start": 5, "end": 13, "probability": 0.8956, "type": "Other", "normalized_text": "Halloween"}], "urls": [{"start": 236, "end": 259, "url": "https://t.co/ihLfQ3U2ki", "expanded_url": "http://flytap.com/flights-tw", "display_url": "flytap.com/flights-tw", "images": [{"url": "https://pbs.twimg.com/news_img/1594741829697929216/p2WXyl9A?format=jpg&name=orig", "width": 700, "height": 255}, {"url": "https://pbs.twimg.com/news_img/1594741829697929216/p2WXyl9A?format=jpg&name=150x150", "width": 150, "height": 150}], "status": 200, "title": "Find Cheap Flights and Deals: Compare & Book | TAP Air Portugal", "description": "Find cheap flights to 80+ destinations in Europe, Africa and the Americas. Compare great offers on Tap flights and enjoy flying with a premiere airline.", "unwound_url": "https://www.flytap.com/en_us/?utm_source=twitter.com&utm_medium=SOCIAL&utm_campaign=BESTOFFERS&utm_content=ORG&anetwork=SOCIAL"}, {"start": 261, "end": 284, "url": "https://t.co/I0QrwRyRBR", "expanded_url": "https://twitter.com/tapairportugal/status/1587044967129747457/photo/1", "display_url": "pic.twitter.com/I0QrwRyRBR", "media_key": "3_1587044713684779010"}, {"start": 261, "end": 284, "url": "https://t.co/I0QrwRyRBR", "expanded_url": "https://twitter.com/tapairportugal/status/1587044967129747457/photo/1", "display_url": "pic.twitter.com/I0QrwRyRBR", "media_key": "3_1587044713684664322"}, {"start": 261, "end": 284, "url": "https://t.co/I0QrwRyRBR", "expanded_url": "https://twitter.com/tapairportugal/status/1587044967129747457/photo/1", "display_url": "pic.twitter.com/I0QrwRyRBR", "media_key": "3_1587044713676390402"}, {"start": 261, "end": 284, "url": "https://t.co/I0QrwRyRBR", "expanded_url": "https://twitter.com/tapairportugal/status/1587044967129747457/photo/1", "display_url": "pic.twitter.com/I0QrwRyRBR", "media_key": "3_1587044713672196097"}]}, "lang": "pt", "created_at": "2022-10-31T11:33:00.000Z", "edit_history_tweet_ids": ["1587044967129747457"], "conversation_id": "1587044967129747457", "author_id": "107472906", "public_metrics": {"retweet_count": 1, "reply_count": 9, "like_count": 9, "quote_count": 0}}, {"text": "@rajeshkal123 @rajeshkal123 Hello RAJESH, can you provide us with your booking code? For security reasons we suggest that you send it by direct message. \nThank you.", "source": "Qualtrics Social Connect", "id": "1587037434608590849", "entities": {"annotations": [{"start": 34, "end": 39, "probability": 0.6638, "type": "Other", "normalized_text": "RAJESH"}], "mentions": [{"start": 0, "end": 13, "username": "rajeshkal123", "id": "194049699"}, {"start": 14, "end": 27, "username": "rajeshkal123", "id": "194049699"}]}, "lang": "en", "in_reply_to_user_id": "194049699", "created_at": "2022-10-31T11:03:04.000Z", "edit_history_tweet_ids": ["1587037434608590849"], "conversation_id": "1587036661904351232", "author_id": "107472906", "public_metrics": {"retweet_count": 0, "reply_count": 1, "like_count": 0, "quote_count": 0}}, {"text": "@risquete @risquete Hola Jaume, hemos contestado por mensaje directo. Gracias.", "source": "Qualtrics Social Connect", "id": "1587027140624670722", "entities": {"annotations": [{"start": 25, "end": 29, "probability": 0.4942, "type": "Other", "normalized_text": "Jaume"}], "mentions": [{"start": 0, "end": 9, "username": "risquete", "id": "214980160"}, {"start": 10, "end": 19, "username": "risquete", "id": "214980160"}]}, "lang": "es", "in_reply_to_user_id": "214980160", "created_at": "2022-10-31T10:22:10.000Z", "edit_history_tweet_ids": ["1587027140624670722"], "conversation_id": "1587023420180598784", "author_id": "107472906", "public_metrics": {"retweet_count": 0, "reply_count": 0, "like_count": 0, "quote_count": 0}}, {"text": "@mikesyard @mikesyard Hello Mike, we are sorry for any constraints. Can you provide us with your booking code so that it can be verified? For security reasons, we suggest that you send it by direct message. \nThank you.", "source": "Qualtrics Social Connect", "id": "1587016572023062530", "entities": {"annotations": [{"start": 28, "end": 31, "probability": 0.6446, "type": "Person", "normalized_text": "Mike"}], "mentions": [{"start": 0, "end": 10, "username": "mikesyard", "id": "59655069"}, {"start": 11, "end": 21, "username": "mikesyard", "id": "59655069"}]}, "lang": "en", "in_reply_to_user_id": "59655069", "created_at": "2022-10-31T09:40:10.000Z", "edit_history_tweet_ids": ["1587016572023062530"], "conversation_id": "1587014569955889152", "author_id": "107472906", "public_metrics": {"retweet_count": 0, "reply_count": 1, "like_count": 0, "quote_count": 0}}, {"text": "@ndfeed @ndfeed Hello, thank you for your words \ud83d\ude42", "source": "Qualtrics Social Connect", "id": "1587014742140456963", "lang": "en", "in_reply_to_user_id": "12275822", "created_at": "2022-10-31T09:32:54.000Z", "edit_history_tweet_ids": ["1587014742140456963"], "conversation_id": "1587012712399257601", "author_id": "107472906", "public_metrics": {"retweet_count": 0, "reply_count": 0, "like_count": 0, "quote_count": 0}, "entities": {"mentions": [{"start": 0, "end": 7, "username": "ndfeed", "id": "12275822"}, {"start": 8, "end": 15, "username": "ndfeed", "id": "12275822"}]}}, {"text": "@iamstevecook @iamstevecook Hello SC, can you provide us with your Tag number and booking code? For security reasons we suggest to send it by direct message. \nThank you.", "source": "Qualtrics Social Connect", "id": "1587004217226584065", "lang": "en", "in_reply_to_user_id": "58467662", "created_at": "2022-10-31T08:51:05.000Z", "edit_history_tweet_ids": ["1587004217226584065"], "conversation_id": "1586999439520153601", "author_id": "107472906", "public_metrics": {"retweet_count": 0, "reply_count": 1, "like_count": 0, "quote_count": 0}, "entities": {"mentions": [{"start": 0, "end": 13, "username": "iamstevecook", "id": "58467662"}, {"start": 14, "end": 27, "username": "iamstevecook", "id": "58467662"}]}}, {"text": "@Attilapia @attilapia Hello Pia, we sincerely regret the inconvenience. Can you provide us with the PIR number, so that it can be verified? For security reasons, we suggest that you send it by direct message. \nThank you.", "source": "Qualtrics Social Connect", "id": "1586999434860167169", "entities": {"annotations": [{"start": 28, "end": 30, "probability": 0.7012, "type": "Other", "normalized_text": "Pia"}], "mentions": [{"start": 0, "end": 10, "username": "Attilapia", "id": "890480767"}, {"start": 11, "end": 21, "username": "Attilapia", "id": "890480767"}]}, "lang": "en", "in_reply_to_user_id": "890480767", "created_at": "2022-10-31T08:32:04.000Z", "edit_history_tweet_ids": ["1586999434860167169"], "conversation_id": "1586997752604524546", "author_id": "107472906", "public_metrics": {"retweet_count": 0, "reply_count": 0, "like_count": 0, "quote_count": 0}}, {"text": "@rosebella2121 @TerrenzVM Hello morgan,\nwe have replied to your DM.\nThank you", "source": "Qualtrics Social Connect", "id": "1586995539492626432", "entities": {"annotations": [{"start": 32, "end": 37, "probability": 0.5124, "type": "Other", "normalized_text": "morgan"}], "mentions": [{"start": 0, "end": 14, "username": "rosebella2121", "id": "1447425996"}, {"start": 15, "end": 25, "username": "TerrenzVM", "id": "39305481"}]}, "lang": "en", "in_reply_to_user_id": "1447425996", "created_at": "2022-10-31T08:16:36.000Z", "edit_history_tweet_ids": ["1586995539492626432"], "conversation_id": "1586829159048925184", "author_id": "107472906", "public_metrics": {"retweet_count": 0, "reply_count": 1, "like_count": 0, "quote_count": 0}}, {"text": "@AsikainenElina @asikainenelina Hello Elina, can you provide us with the complaint number, so that it can be verified? For security reasons we suggest that you do it by direct message. \nThank you.", "source": "Qualtrics Social Connect", "id": "1586993348367118336", "entities": {"annotations": [{"start": 38, "end": 42, "probability": 0.7089, "type": "Other", "normalized_text": "Elina"}], "mentions": [{"start": 0, "end": 15, "username": "AsikainenElina", "id": "1480167472741421058"}, {"start": 16, "end": 31, "username": "AsikainenElina", "id": "1480167472741421058"}]}, "lang": "en", "in_reply_to_user_id": "1480167472741421058", "created_at": "2022-10-31T08:07:53.000Z", "edit_history_tweet_ids": ["1586993348367118336"], "conversation_id": "1586960869984018433", "author_id": "107472906", "public_metrics": {"retweet_count": 0, "reply_count": 1, "like_count": 0, "quote_count": 0}}, {"text": "@NikkiChagra @nikkichagra Hello Nicole, we sincerely apologize for the inconvenience. Can you please provide us with that PIR code regarding your lost property? For security reasons, we suggest that you send it by direct message. \nThank you.", "source": "Qualtrics Social Connect", "id": "1586992932032110592", "entities": {"annotations": [{"start": 32, "end": 37, "probability": 0.5332, "type": "Person", "normalized_text": "Nicole"}], "mentions": [{"start": 0, "end": 12, "username": "NikkiChagra", "id": "1423990612802609159"}, {"start": 13, "end": 25, "username": "NikkiChagra", "id": "1423990612802609159"}]}, "lang": "en", "in_reply_to_user_id": "1423990612802609159", "created_at": "2022-10-31T08:06:14.000Z", "edit_history_tweet_ids": ["1586992932032110592"], "conversation_id": "1586929897347358720", "author_id": "107472906", "public_metrics": {"retweet_count": 0, "reply_count": 1, "like_count": 0, "quote_count": 0}}, {"text": "@ANGIEPOPS11 @angiepops11 Hello Angelique, we sincerely regret that the experience did not meet your expectations. If we can help with some question through this channel, please let us know.\nThank you.", "source": "Qualtrics Social Connect", "id": "1586990984923336705", "entities": {"annotations": [{"start": 32, "end": 40, "probability": 0.6371, "type": "Other", "normalized_text": "Angelique"}], "mentions": [{"start": 0, "end": 12, "username": "ANGIEPOPS11", "id": "57639281"}, {"start": 13, "end": 25, "username": "ANGIEPOPS11", "id": "57639281"}]}, "lang": "en", "in_reply_to_user_id": "57639281", "created_at": "2022-10-31T07:58:30.000Z", "edit_history_tweet_ids": ["1586990984923336705"], "conversation_id": "1586912022909837313", "author_id": "107472906", "public_metrics": {"retweet_count": 0, "reply_count": 1, "like_count": 0, "quote_count": 0}}, {"text": "@Shon70399056 @shon70399056 Hello, we sincerely apologize for the inconvenience. \nWe verified that your claim has been successfully submitted and that it is still under analysis. As soon as the analysis is concluded you will receive a reply by e-mail.\nWe kindly ask you to wait. Thank you.", "source": "Qualtrics Social Connect", "id": "1586987014875774978", "lang": "en", "in_reply_to_user_id": "987907015287672832", "created_at": "2022-10-31T07:42:43.000Z", "edit_history_tweet_ids": ["1586987014875774978"], "conversation_id": "1586884138946203651", "author_id": "107472906", "public_metrics": {"retweet_count": 0, "reply_count": 0, "like_count": 0, "quote_count": 0}, "entities": {"mentions": [{"start": 0, "end": 13, "username": "Shon70399056", "id": "987907015287672832"}, {"start": 14, "end": 27, "username": "Shon70399056", "id": "987907015287672832"}]}}, {"text": "@forrwithmycat Hola myswetheart, \u00bfpuede indicarnos el c\u00f3digo de reserva, por favor? Por razones de seguridad, le sugerimos que lo haga por mensaje privado. Gracias.", "source": "Qualtrics Social Connect", "id": "1586858089705111552", "entities": {"annotations": [{"start": 20, "end": 30, "probability": 0.778, "type": "Other", "normalized_text": "myswetheart"}], "mentions": [{"start": 0, "end": 14, "username": "forrwithmycat", "id": "1586605321950269440"}]}, "lang": "es", "in_reply_to_user_id": "1586605321950269440", "created_at": "2022-10-30T23:10:25.000Z", "edit_history_tweet_ids": ["1586858089705111552"], "conversation_id": "1586854833977532417", "author_id": "107472906", "public_metrics": {"retweet_count": 0, "reply_count": 1, "like_count": 0, "quote_count": 0}}, {"text": "@Smvmc89 Ol\u00e1 Sandra,\n\npoderia nos indicar, por mensagem privada, o seu n\u00famero de processo de reclama\u00e7\u00e3o e endere\u00e7o de email associado, para que possamos verificar, por favor? Obrigado.", "source": "Qualtrics Social Connect", "id": "1586857913582239745", "entities": {"annotations": [{"start": 13, "end": 18, "probability": 0.639, "type": "Person", "normalized_text": "Sandra"}], "mentions": [{"start": 0, "end": 8, "username": "Smvmc89", "id": "940336346819973122"}]}, "lang": "pt", "in_reply_to_user_id": "940336346819973122", "created_at": "2022-10-30T23:09:43.000Z", "edit_history_tweet_ids": ["1586857913582239745"], "conversation_id": "1562495828006019074", "author_id": "107472906", "public_metrics": {"retweet_count": 0, "reply_count": 2, "like_count": 0, "quote_count": 0}}, {"text": "@alicolas22 Bonjour Lili,\nnous avons r\u00e9pondu par DM.\nMerci.", "source": "Qualtrics Social Connect", "id": "1586848793177341954", "lang": "fr", "in_reply_to_user_id": "1431284777886306306", "created_at": "2022-10-30T22:33:29.000Z", "edit_history_tweet_ids": ["1586848793177341954"], "conversation_id": "1586839544200044546", "author_id": "107472906", "public_metrics": {"retweet_count": 0, "reply_count": 1, "like_count": 0, "quote_count": 0}, "entities": {"mentions": [{"start": 0, "end": 11, "username": "alicolas22", "id": "1431284777886306306"}]}}, {"text": "@TerrenzVM Hello Terrence,\n\ncan you inform us through DM your booking reference or electronic ticket number (047...) so we may verify? The arrangement of possible accommodation can only managed at the airport staff directly and not over this channel.", "source": "Qualtrics Social Connect", "id": "1586836446433972225", "entities": {"annotations": [{"start": 17, "end": 24, "probability": 0.5947, "type": "Other", "normalized_text": "Terrence"}], "mentions": [{"start": 0, "end": 10, "username": "TerrenzVM", "id": "39305481"}]}, "lang": "en", "in_reply_to_user_id": "39305481", "created_at": "2022-10-30T21:44:25.000Z", "edit_history_tweet_ids": ["1586836446433972225"], "conversation_id": "1586829159048925184", "author_id": "107472906", "public_metrics": {"retweet_count": 0, "reply_count": 0, "like_count": 0, "quote_count": 0}}, {"text": "@KarryMelchiades Ol\u00e1 Karry,\nRespondemos por mensagem privada.\nObrigada.", "source": "Qualtrics Social Connect", "id": "1586818862783369219", "entities": {"annotations": [{"start": 21, "end": 25, "probability": 0.6275, "type": "Other", "normalized_text": "Karry"}], "mentions": [{"start": 0, "end": 16, "username": "KarryMelchiades", "id": "1229125723371266048"}]}, "lang": "pt", "in_reply_to_user_id": "1229125723371266048", "created_at": "2022-10-30T20:34:33.000Z", "edit_history_tweet_ids": ["1586818862783369219"], "conversation_id": "1569244974931415041", "author_id": "107472906", "public_metrics": {"retweet_count": 0, "reply_count": 0, "like_count": 0, "quote_count": 0}}, {"text": "@TalesLisboa2 Tales,\nwe have answered through DM.\nThank you.", "source": "Qualtrics Social Connect", "id": "1586811329540915200", "entities": {"annotations": [{"start": 14, "end": 18, "probability": 0.7602, "type": "Other", "normalized_text": "Tales"}], "mentions": [{"start": 0, "end": 13, "username": "TalesLisboa2", "id": "1581262025493192704"}]}, "lang": "en", "in_reply_to_user_id": "1581262025493192704", "created_at": "2022-10-30T20:04:37.000Z", "edit_history_tweet_ids": ["1586811329540915200"], "conversation_id": "1586031604245606400", "author_id": "107472906", "public_metrics": {"retweet_count": 0, "reply_count": 0, "like_count": 0, "quote_count": 0}}, {"text": "@Dynamo17Pratik Hello Patrik,\n\nthe airlines are not responsible for informing passenger which documentation or requirements are mandatory in order to enter in a certain country. All information necessary to travel are full responsibility of the passengers. Thank you.", "source": "Qualtrics Social Connect", "id": "1586804364747755521", "context_annotations": [{"domain": {"id": "46", "name": "Business Taxonomy", "description": "Categories within Brand Verticals that narrow down the scope of Brands"}, "entity": {"id": "1557697439489880065", "name": "Travel & Transportation Business", "description": "Brands, companies, advertisers and every non-person handle with the profit intent related to travel as airlines, travel agencies, hotels"}}, {"domain": {"id": "30", "name": "Entities [Entity Service]", "description": "Entity Service top level domain, every item that is in Entity Service should be in this domain"}, "entity": {"id": "839159814991167489", "name": "Travel", "description": "Travel"}}, {"domain": {"id": "67", "name": "Interests and Hobbies", "description": "Interests, opinions, and behaviors of individuals, groups, or cultures; like Speciality Cooking or Theme Parks"}, "entity": {"id": "839161975712067584", "name": "Travel Actions", "description": "This entity includes all conversations about travel and vacation."}}], "entities": {"annotations": [{"start": 22, "end": 27, "probability": 0.3897, "type": "Place", "normalized_text": "Patrik"}], "mentions": [{"start": 0, "end": 15, "username": "Dynamo17Pratik", "id": "856920506"}]}, "lang": "en", "in_reply_to_user_id": "856920506", "created_at": "2022-10-30T19:36:56.000Z", "edit_history_tweet_ids": ["1586804364747755521"], "conversation_id": "1586795071860625408", "author_id": "107472906", "public_metrics": {"retweet_count": 0, "reply_count": 3, "like_count": 0, "quote_count": 0}}, {"text": "@MikeCroon Hello Mike,\nWe kindly request you to provide us your email address, the booking reference, the claims file number and what you want to add to your complaint. \nDue to confidentiality reasons, we suggest you to do it through DM. Thank you.", "source": "Qualtrics Social Connect", "id": "1586784201877196804", "entities": {"annotations": [{"start": 17, "end": 20, "probability": 0.6821, "type": "Person", "normalized_text": "Mike"}], "mentions": [{"start": 0, "end": 10, "username": "MikeCroon", "id": "1586779081852555264"}]}, "lang": "en", "in_reply_to_user_id": "1586779081852555264", "created_at": "2022-10-30T18:16:49.000Z", "edit_history_tweet_ids": ["1586784201877196804"], "conversation_id": "951826393205223424", "author_id": "107472906", "public_metrics": {"retweet_count": 0, "reply_count": 0, "like_count": 0, "quote_count": 0}}, {"text": "@TalesLisboa2 Hello Tales,\nwe have answered through DM.\nThank you.", "source": "Qualtrics Social Connect", "id": "1586766374793547776", "entities": {"annotations": [{"start": 20, "end": 24, "probability": 0.8643, "type": "Other", "normalized_text": "Tales"}], "mentions": [{"start": 0, "end": 13, "username": "TalesLisboa2", "id": "1581262025493192704"}]}, "lang": "en", "in_reply_to_user_id": "1581262025493192704", "created_at": "2022-10-30T17:05:59.000Z", "edit_history_tweet_ids": ["1586766374793547776"], "conversation_id": "1586031604245606400", "author_id": "107472906", "public_metrics": {"retweet_count": 0, "reply_count": 1, "like_count": 0, "quote_count": 0}}, {"text": "@Run_itt Can you inform us thr through DM your complaint file number and email adress related so we may verify? Thank you.", "source": "Qualtrics Social Connect", "id": "1586762264442544129", "lang": "en", "in_reply_to_user_id": "3096799408", "created_at": "2022-10-30T16:49:39.000Z", "edit_history_tweet_ids": ["1586762264442544129"], "conversation_id": "1586759652796243976", "author_id": "107472906", "public_metrics": {"retweet_count": 0, "reply_count": 1, "like_count": 0, "quote_count": 0}, "entities": {"mentions": [{"start": 0, "end": 8, "username": "Run_itt", "id": "3096799408"}]}}, {"text": "@Run_itt Hello Ronit,\n\nhow may we assist you? Can you clarify through DM your situation so we may verify? Thank you.", "source": "Qualtrics Social Connect", "id": "1586760993291599875", "entities": {"annotations": [{"start": 15, "end": 19, "probability": 0.5286, "type": "Other", "normalized_text": "Ronit"}], "mentions": [{"start": 0, "end": 8, "username": "Run_itt", "id": "3096799408"}]}, "lang": "en", "in_reply_to_user_id": "3096799408", "created_at": "2022-10-30T16:44:36.000Z", "edit_history_tweet_ids": ["1586760993291599875"], "conversation_id": "1586759652796243976", "author_id": "107472906", "public_metrics": {"retweet_count": 0, "reply_count": 2, "like_count": 0, "quote_count": 0}}, {"text": "@ArisDama Ol\u00e1 Aris,\nInformamos que respondemos \u00e0 sua mensagem privada. Informamos tamb\u00e9m que as refei\u00e7\u00f5es especiais devem ser solicitadas com anteced\u00eancia. Esta informa\u00e7\u00e3o est\u00e1 dispon\u00edvel no nosso site.\nObrigado", "source": "Qualtrics Social Connect", "id": "1586749200301268993", "entities": {"annotations": [{"start": 14, "end": 17, "probability": 0.5462, "type": "Other", "normalized_text": "Aris"}], "mentions": [{"start": 0, "end": 9, "username": "ArisDama", "id": "58855024"}]}, "lang": "pt", "in_reply_to_user_id": "58855024", "created_at": "2022-10-30T15:57:44.000Z", "edit_history_tweet_ids": ["1586749200301268993"], "conversation_id": "1586661840653778945", "author_id": "107472906", "public_metrics": {"retweet_count": 0, "reply_count": 3, "like_count": 0, "quote_count": 0}}, {"text": "@iurifarenzena Ol\u00e1 Iuri,\nInformamos que respondemos \u00e0 sua mensagem privada.\nObrigado", "source": "Qualtrics Social Connect", "id": "1586747637352599560", "entities": {"annotations": [{"start": 19, "end": 22, "probability": 0.6936, "type": "Other", "normalized_text": "Iuri"}], "mentions": [{"start": 0, "end": 14, "username": "iurifarenzena", "id": "52180053"}]}, "lang": "pt", "in_reply_to_user_id": "52180053", "created_at": "2022-10-30T15:51:31.000Z", "edit_history_tweet_ids": ["1586747637352599560"], "conversation_id": "1585435516841123841", "author_id": "107472906", "public_metrics": {"retweet_count": 0, "reply_count": 1, "like_count": 0, "quote_count": 0}}, {"text": "@Rodrig0Salgado Hello Rodrigo,\nwe have replied to your DM.\nThank you", "source": "Qualtrics Social Connect", "id": "1586745996284989442", "entities": {"annotations": [{"start": 22, "end": 28, "probability": 0.5528, "type": "Person", "normalized_text": "Rodrigo"}], "mentions": [{"start": 0, "end": 15, "username": "Rodrig0Salgado", "id": "26698036"}]}, "lang": "en", "in_reply_to_user_id": "26698036", "created_at": "2022-10-30T15:45:00.000Z", "edit_history_tweet_ids": ["1586745996284989442"], "conversation_id": "1584065235362623488", "author_id": "107472906", "public_metrics": {"retweet_count": 0, "reply_count": 1, "like_count": 0, "quote_count": 0}}, {"text": "@utpandey Hello Utkarsh,\nwe have answered through DM.\nThank you.", "source": "Qualtrics Social Connect", "id": "1586743315340435456", "entities": {"annotations": [{"start": 16, "end": 22, "probability": 0.6276, "type": "Other", "normalized_text": "Utkarsh"}], "mentions": [{"start": 0, "end": 9, "username": "utpandey", "id": "826834231"}]}, "lang": "en", "in_reply_to_user_id": "826834231", "created_at": "2022-10-30T15:34:21.000Z", "edit_history_tweet_ids": ["1586743315340435456"], "conversation_id": "1586734593566441473", "author_id": "107472906", "public_metrics": {"retweet_count": 0, "reply_count": 1, "like_count": 0, "quote_count": 0}}, {"text": "@DrLiz16 Hello Elizabeth,\nwe have answered through DM.\nThank you.", "source": "Qualtrics Social Connect", "id": "1586740392292192262", "entities": {"annotations": [{"start": 15, "end": 23, "probability": 0.6845, "type": "Person", "normalized_text": "Elizabeth"}], "mentions": [{"start": 0, "end": 8, "username": "DrLiz16", "id": "981277278612180992"}]}, "lang": "en", "in_reply_to_user_id": "981277278612180992", "created_at": "2022-10-30T15:22:44.000Z", "edit_history_tweet_ids": ["1586740392292192262"], "conversation_id": "1586031604245606400", "author_id": "107472906", "public_metrics": {"retweet_count": 0, "reply_count": 1, "like_count": 0, "quote_count": 0}}, {"text": "@Prof_Baptista Agradecemos o envio da informa\u00e7\u00e3o.\nCaso necessite de alguma ajuda adicional, n\u00e3o hesite em contactar-nos. (2/2)", "source": "Qualtrics Social Connect", "id": "1586738795361320963", "lang": "pt", "in_reply_to_user_id": "422895602", "created_at": "2022-10-30T15:16:23.000Z", "edit_history_tweet_ids": ["1586738795361320963"], "conversation_id": "1586735383534092291", "author_id": "107472906", "public_metrics": {"retweet_count": 0, "reply_count": 0, "like_count": 0, "quote_count": 0}, "entities": {"mentions": [{"start": 0, "end": 14, "username": "Prof_Baptista", "id": "422895602"}]}}, {"text": "@Prof_Baptista Ol\u00e1 Nuno,\nLamentamos a situa\u00e7\u00e3o reportada bem como o inconveniente causado. \nInformamos que o o seu coment\u00e1rio foi encaminhado para a \u00e1rea respons\u00e1vel, de forma a permitir um processo de melhoria cont\u00ednua dos servi\u00e7os prestados. (1/2)", "source": "Qualtrics Social Connect", "id": "1586738735349174278", "entities": {"annotations": [{"start": 19, "end": 22, "probability": 0.9445, "type": "Person", "normalized_text": "Nuno"}], "mentions": [{"start": 0, "end": 14, "username": "Prof_Baptista", "id": "422895602"}]}, "lang": "pt", "in_reply_to_user_id": "422895602", "created_at": "2022-10-30T15:16:09.000Z", "edit_history_tweet_ids": ["1586738735349174278"], "conversation_id": "1586735383534092291", "author_id": "107472906", "public_metrics": {"retweet_count": 0, "reply_count": 0, "like_count": 0, "quote_count": 0}}, {"text": "@iurifarenzena Iuri,\nPedimos ent\u00e3o que nos indique por favor o seu endere\u00e7o de email para verifica\u00e7\u00e3o. Recomendamos que o fa\u00e7a por mensagem privada devido a raz\u00f5es de confidencialidade de dados.\nObrigado", "source": "Qualtrics Social Connect", "id": "1586733384298074113", "entities": {"annotations": [{"start": 15, "end": 18, "probability": 0.6064, "type": "Other", "normalized_text": "Iuri"}], "mentions": [{"start": 0, "end": 14, "username": "iurifarenzena", "id": "52180053"}]}, "lang": "pt", "in_reply_to_user_id": "52180053", "created_at": "2022-10-30T14:54:53.000Z", "edit_history_tweet_ids": ["1586733384298074113"], "conversation_id": "1585435516841123841", "author_id": "107472906", "public_metrics": {"retweet_count": 0, "reply_count": 1, "like_count": 0, "quote_count": 0}}, {"text": "@Rodrig0Salgado Hello Rodrigo,\nwe have replied to your DM.\nThank you", "source": "Qualtrics Social Connect", "id": "1586733033817792513", "entities": {"annotations": [{"start": 22, "end": 28, "probability": 0.5528, "type": "Person", "normalized_text": "Rodrigo"}], "mentions": [{"start": 0, "end": 15, "username": "Rodrig0Salgado", "id": "26698036"}]}, "lang": "en", "in_reply_to_user_id": "26698036", "created_at": "2022-10-30T14:53:29.000Z", "edit_history_tweet_ids": ["1586733033817792513"], "conversation_id": "1584065235362623488", "author_id": "107472906", "public_metrics": {"retweet_count": 0, "reply_count": 1, "like_count": 0, "quote_count": 0}}, {"text": "@iurifarenzena Ol\u00e1 Iuri,\nSugerimos que tente novamente utilizando um browser diferente do que est\u00e1 a utilizar neste momento e que limpe os cookies antes de tentar novamente.\nObrigado", "source": "Qualtrics Social Connect", "id": "1586732207770591232", "entities": {"annotations": [{"start": 19, "end": 22, "probability": 0.7839, "type": "Other", "normalized_text": "Iuri"}], "mentions": [{"start": 0, "end": 14, "username": "iurifarenzena", "id": "52180053"}]}, "lang": "pt", "in_reply_to_user_id": "52180053", "created_at": "2022-10-30T14:50:13.000Z", "edit_history_tweet_ids": ["1586732207770591232"], "conversation_id": "1585435516841123841", "author_id": "107472906", "public_metrics": {"retweet_count": 0, "reply_count": 1, "like_count": 0, "quote_count": 0}}, {"text": "@Marion_Adln De rien, Marion.\nNous restons \u00e0 votre disposition pour tout renseignement compl\u00e9mentaire. Merci.", "source": "Qualtrics Social Connect", "id": "1586732106599776256", "lang": "fr", "in_reply_to_user_id": "1447508709555507209", "created_at": "2022-10-30T14:49:48.000Z", "edit_history_tweet_ids": ["1586732106599776256"], "conversation_id": "1585633924155207680", "author_id": "107472906", "public_metrics": {"retweet_count": 0, "reply_count": 0, "like_count": 0, "quote_count": 0}, "entities": {"mentions": [{"start": 0, "end": 12, "username": "Marion_Adln", "id": "1447508709555507209"}]}}, {"text": "@MJOneDone For confidentiality reasons, we suggest you send it by private message. Thank you in advance.  2/2", "source": "Qualtrics Social Connect", "id": "1586728811500036098", "lang": "en", "in_reply_to_user_id": "311728138", "created_at": "2022-10-30T14:36:43.000Z", "edit_history_tweet_ids": ["1586728811500036098"], "conversation_id": "1586722706657001474", "author_id": "107472906", "public_metrics": {"retweet_count": 0, "reply_count": 1, "like_count": 0, "quote_count": 0}, "entities": {"mentions": [{"start": 0, "end": 10, "username": "MJOneDone", "id": "311728138"}]}}, {"text": "@MJOneDone Hello MJRunner, we apologise for all the distress caused by this situation. In order to verify the information, can you please inform us your complaints reference number and your email address? 1/2", "source": "Qualtrics Social Connect", "id": "1586728795104595968", "entities": {"annotations": [{"start": 17, "end": 24, "probability": 0.5233, "type": "Other", "normalized_text": "MJRunner"}], "mentions": [{"start": 0, "end": 10, "username": "MJOneDone", "id": "311728138"}]}, "lang": "en", "in_reply_to_user_id": "311728138", "created_at": "2022-10-30T14:36:39.000Z", "edit_history_tweet_ids": ["1586728795104595968"], "conversation_id": "1586722706657001474", "author_id": "107472906", "public_metrics": {"retweet_count": 0, "reply_count": 0, "like_count": 0, "quote_count": 0}}, {"text": "@Guerin_Marie @TF1Info @LCI @RTLFrance @Europe1 @courbet_julien Bonjour Marie,\nNous vous informons que la situation est en cours de v\u00e9rification. Vous recevrez une r\u00e9ponse dans les plus brefs d\u00e9lais par email \u00e0 ce sujet.\nMerci", "source": "Qualtrics Social Connect", "id": "1586728595115868161", "context_annotations": [{"domain": {"id": "45", "name": "Brand Vertical", "description": "Top level entities that describe a Brands industry"}, "entity": {"id": "781974597310615553", "name": "Entertainment"}}, {"domain": {"id": "30", "name": "Entities [Entity Service]", "description": "Entity Service top level domain, every item that is in Entity Service should be in this domain"}, "entity": {"id": "781974597105094656", "name": "TV/Movies Related - Entertainment"}}, {"domain": {"id": "47", "name": "Brand", "description": "Brands and Companies"}, "entity": {"id": "1108063658704162816", "name": "TF1", "description": "TF1"}}], "lang": "fr", "in_reply_to_user_id": "478501702", "created_at": "2022-10-30T14:35:51.000Z", "edit_history_tweet_ids": ["1586728595115868161"], "conversation_id": "1586716385215930368", "author_id": "107472906", "public_metrics": {"retweet_count": 0, "reply_count": 0, "like_count": 0, "quote_count": 0}, "entities": {"mentions": [{"start": 0, "end": 13, "username": "Guerin_Marie", "id": "478501702"}, {"start": 14, "end": 22, "username": "TF1Info", "id": "3390775469"}, {"start": 23, "end": 27, "username": "LCI", "id": "26110930"}, {"start": 28, "end": 38, "username": "RTLFrance", "id": "34294667"}, {"start": 39, "end": 47, "username": "Europe1", "id": "34570323"}, {"start": 48, "end": 63, "username": "courbet_julien", "id": "828931483"}]}}, {"text": "@JohanMuijres Hello Johan,\nwe have replied to your DM.\nThank you", "source": "Qualtrics Social Connect", "id": "1586727509345075200", "entities": {"annotations": [{"start": 20, "end": 24, "probability": 0.59, "type": "Person", "normalized_text": "Johan"}], "mentions": [{"start": 0, "end": 13, "username": "JohanMuijres", "id": "67011819"}]}, "lang": "en", "in_reply_to_user_id": "67011819", "created_at": "2022-10-30T14:31:32.000Z", "edit_history_tweet_ids": ["1586727509345075200"], "conversation_id": "1585674811124113408", "author_id": "107472906", "public_metrics": {"retweet_count": 0, "reply_count": 2, "like_count": 0, "quote_count": 0}}, {"text": "@EddieLee42 Hello Eddie, we are sorry that the service did not meet your expectations. If we can help with some question through this channel, please let us know. \nThank you.", "source": "Qualtrics Social Connect", "id": "1586724585797558277", "entities": {"annotations": [{"start": 18, "end": 22, "probability": 0.7586, "type": "Person", "normalized_text": "Eddie"}], "mentions": [{"start": 0, "end": 11, "username": "EddieLee42", "id": "1543721616"}]}, "lang": "en", "in_reply_to_user_id": "1543721616", "created_at": "2022-10-30T14:19:55.000Z", "edit_history_tweet_ids": ["1586724585797558277"], "conversation_id": "1586031604245606400", "author_id": "107472906", "public_metrics": {"retweet_count": 0, "reply_count": 0, "like_count": 0, "quote_count": 0}}, {"text": "@yu26440222 Hello yu, we have replied by private message. Thank you.", "source": "Qualtrics Social Connect", "id": "1586718782181068807", "lang": "en", "in_reply_to_user_id": "1583158278871449600", "created_at": "2022-10-30T13:56:52.000Z", "edit_history_tweet_ids": ["1586718782181068807"], "conversation_id": "1583038479990038528", "author_id": "107472906", "public_metrics": {"retweet_count": 0, "reply_count": 0, "like_count": 0, "quote_count": 0}, "entities": {"mentions": [{"start": 0, "end": 11, "username": "yu26440222", "id": "1583158278871449600"}]}}, {"text": "@Manchestnero Hello Miguel,\nwe have replied to your DM.\nThank you", "source": "Qualtrics Social Connect", "id": "1586710421607796744", "entities": {"annotations": [{"start": 20, "end": 25, "probability": 0.5929, "type": "Person", "normalized_text": "Miguel"}], "mentions": [{"start": 0, "end": 13, "username": "Manchestnero", "id": "588571606"}]}, "lang": "en", "in_reply_to_user_id": "588571606", "created_at": "2022-10-30T13:23:38.000Z", "edit_history_tweet_ids": ["1586710421607796744"], "conversation_id": "1548993285045338113", "author_id": "107472906", "public_metrics": {"retweet_count": 0, "reply_count": 0, "like_count": 0, "quote_count": 0}}, {"text": "@benedetta_dc Hello Benedetta, we have replied to your private message. Thank you.", "source": "Qualtrics Social Connect", "id": "1586709808417226753", "entities": {"annotations": [{"start": 20, "end": 28, "probability": 0.5237, "type": "Other", "normalized_text": "Benedetta"}], "mentions": [{"start": 0, "end": 13, "username": "benedetta_dc", "id": "3417520654"}]}, "lang": "en", "in_reply_to_user_id": "3417520654", "created_at": "2022-10-30T13:21:12.000Z", "edit_history_tweet_ids": ["1586709808417226753"], "conversation_id": "1586670726941130752", "author_id": "107472906", "public_metrics": {"retweet_count": 0, "reply_count": 0, "like_count": 0, "quote_count": 0}}, {"text": "@StefaniBertrand @dgccrf @DGAC Bonjour BertrandStefani,\nNous vous prions de nous indiquer votre num\u00e9ro de r\u00e9clamation et votre adresse email afin que nous puissions v\u00e9rifier cette situation.\nNous vous recommandons de le faire par message priv\u00e9 pour des raisons de confidentialit\u00e9. \nMerci", "source": "Qualtrics Social Connect", "id": "1586709659787923457", "lang": "fr", "in_reply_to_user_id": "1000066766033358849", "created_at": "2022-10-30T13:20:37.000Z", "edit_history_tweet_ids": ["1586709659787923457"], "conversation_id": "1586707633624547328", "author_id": "107472906", "public_metrics": {"retweet_count": 0, "reply_count": 1, "like_count": 0, "quote_count": 0}, "entities": {"mentions": [{"start": 0, "end": 16, "username": "StefaniBertrand", "id": "1000066766033358849"}, {"start": 17, "end": 24, "username": "dgccrf", "id": "415594401"}, {"start": 25, "end": 30, "username": "DGAC", "id": "224140014"}]}}, {"text": "@SuriR Hello Suri, we have replied to your private message. Thank you.", "source": "Qualtrics Social Connect", "id": "1586706750417272841", "entities": {"annotations": [{"start": 13, "end": 16, "probability": 0.7515, "type": "Other", "normalized_text": "Suri"}], "mentions": [{"start": 0, "end": 6, "username": "SuriR", "id": "21924681"}]}, "lang": "en", "in_reply_to_user_id": "21924681", "created_at": "2022-10-30T13:09:03.000Z", "edit_history_tweet_ids": ["1586706750417272841"], "conversation_id": "1586669562333995010", "author_id": "107472906", "public_metrics": {"retweet_count": 0, "reply_count": 0, "like_count": 0, "quote_count": 0}}, {"text": "@Santambreus @ItalyinPortugal @turismoportugal @dntwit Hello Nicol\u00f2.\nThank you for the information.\nIf our assistance is still needed, please let us know.\nThank you", "source": "Qualtrics Social Connect", "id": "1586706015407558663", "entities": {"annotations": [{"start": 61, "end": 66, "probability": 0.5623, "type": "Other", "normalized_text": "Nicol\u00f2"}], "mentions": [{"start": 0, "end": 12, "username": "Santambreus", "id": "59471800"}, {"start": 13, "end": 29, "username": "ItalyinPortugal", "id": "991683256360886273"}, {"start": 30, "end": 46, "username": "turismoportugal", "id": "19903099"}, {"start": 47, "end": 54, "username": "dntwit", "id": "395388847"}]}, "lang": "en", "in_reply_to_user_id": "59471800", "created_at": "2022-10-30T13:06:08.000Z", "edit_history_tweet_ids": ["1586706015407558663"], "conversation_id": "1586668050404806657", "author_id": "107472906", "public_metrics": {"retweet_count": 0, "reply_count": 0, "like_count": 0, "quote_count": 0}}, {"text": "@Manchestnero Hello Miguel,\nPlease let us know your claim number and email address so that we can check this situation.  We recommend that you do so by private message due to confidentiality reasons.\nThank you", "source": "Qualtrics Social Connect", "id": "1586703158222405633", "entities": {"annotations": [{"start": 20, "end": 25, "probability": 0.7297, "type": "Person", "normalized_text": "Miguel"}], "mentions": [{"start": 0, "end": 13, "username": "Manchestnero", "id": "588571606"}]}, "lang": "en", "in_reply_to_user_id": "588571606", "created_at": "2022-10-30T12:54:47.000Z", "edit_history_tweet_ids": ["1586703158222405633"], "conversation_id": "1548993285045338113", "author_id": "107472906", "public_metrics": {"retweet_count": 0, "reply_count": 1, "like_count": 0, "quote_count": 0}}, {"text": "@hannahmc38 Hello Hannah,\nwe have replied to your DM.\nThank you", "source": "Qualtrics Social Connect", "id": "1586696590848311297", "entities": {"annotations": [{"start": 18, "end": 23, "probability": 0.6588, "type": "Person", "normalized_text": "Hannah"}], "mentions": [{"start": 0, "end": 11, "username": "hannahmc38", "id": "68130004"}]}, "lang": "en", "in_reply_to_user_id": "68130004", "created_at": "2022-10-30T12:28:41.000Z", "edit_history_tweet_ids": ["1586696590848311297"], "conversation_id": "1586694808550182913", "author_id": "107472906", "public_metrics": {"retweet_count": 0, "reply_count": 0, "like_count": 0, "quote_count": 0}}, {"text": "@Santambreus Hello Nicol\u00f2, can you provide with the booking code, so that it can be verified?\nFor security reasons we suggest that you send it by direct message. Thank you.", "source": "Qualtrics Social Connect", "id": "1586694299852455939", "entities": {"annotations": [{"start": 19, "end": 24, "probability": 0.6102, "type": "Person", "normalized_text": "Nicol\u00f2"}], "mentions": [{"start": 0, "end": 12, "username": "Santambreus", "id": "59471800"}]}, "lang": "en", "in_reply_to_user_id": "59471800", "created_at": "2022-10-30T12:19:35.000Z", "edit_history_tweet_ids": ["1586694299852455939"], "conversation_id": "1586668050404806657", "author_id": "107472906", "public_metrics": {"retweet_count": 0, "reply_count": 1, "like_count": 0, "quote_count": 0}}, {"text": "@injuredcheetah Hello Siddant, we have replied to your DM. Thank you.", "source": "Qualtrics Social Connect", "id": "1586693217931640835", "entities": {"annotations": [{"start": 22, "end": 28, "probability": 0.5556, "type": "Other", "normalized_text": "Siddant"}], "mentions": [{"start": 0, "end": 15, "username": "injuredcheetah", "id": "3300502500"}]}, "lang": "en", "in_reply_to_user_id": "3300502500", "created_at": "2022-10-30T12:15:17.000Z", "edit_history_tweet_ids": ["1586693217931640835"], "conversation_id": "1586238706427387905", "author_id": "107472906", "public_metrics": {"retweet_count": 0, "reply_count": 0, "like_count": 1, "quote_count": 0}}, {"text": "@JohanMuijres Hello Johan,\nWe inform you that we will contact you as soon as we have new information on this matter.\nThank you", "source": "Qualtrics Social Connect", "id": "1586684825469161474", "entities": {"annotations": [{"start": 20, "end": 24, "probability": 0.7097, "type": "Person", "normalized_text": "Johan"}], "mentions": [{"start": 0, "end": 13, "username": "JohanMuijres", "id": "67011819"}]}, "lang": "en", "in_reply_to_user_id": "67011819", "created_at": "2022-10-30T11:41:56.000Z", "edit_history_tweet_ids": ["1586684825469161474"], "conversation_id": "1585674811124113408", "author_id": "107472906", "public_metrics": {"retweet_count": 0, "reply_count": 2, "like_count": 0, "quote_count": 0}}, {"text": "@shay_muc Hello Miss Shay,\nwe have replied to your DM.\nThank you", "source": "Qualtrics Social Connect", "id": "1586669267860193280", "entities": {"annotations": [{"start": 21, "end": 24, "probability": 0.6887, "type": "Other", "normalized_text": "Shay"}], "mentions": [{"start": 0, "end": 9, "username": "shay_muc", "id": "395525375"}]}, "lang": "en", "in_reply_to_user_id": "395525375", "created_at": "2022-10-30T10:40:07.000Z", "edit_history_tweet_ids": ["1586669267860193280"], "conversation_id": "1583038479990038528", "author_id": "107472906", "public_metrics": {"retweet_count": 0, "reply_count": 0, "like_count": 0, "quote_count": 0}}, {"text": "@c1othes11 Hello Kevin, we have replied by private message. Thank you.", "source": "Qualtrics Social Connect", "id": "1586660386178273282", "entities": {"annotations": [{"start": 17, "end": 21, "probability": 0.6729, "type": "Person", "normalized_text": "Kevin"}], "mentions": [{"start": 0, "end": 10, "username": "c1othes11", "id": "2324101719"}]}, "lang": "en", "in_reply_to_user_id": "2324101719", "created_at": "2022-10-30T10:04:49.000Z", "edit_history_tweet_ids": ["1586660386178273282"], "conversation_id": "1586638092198465537", "author_id": "107472906", "public_metrics": {"retweet_count": 0, "reply_count": 0, "like_count": 0, "quote_count": 0}}, {"text": "@ArisDama Ol\u00e1 Aris,\nInformamos que respondemos \u00e0 sua mensagem privada.\nObrigado", "source": "Qualtrics Social Connect", "id": "1586655113799671809", "entities": {"annotations": [{"start": 14, "end": 17, "probability": 0.5695, "type": "Other", "normalized_text": "Aris"}], "mentions": [{"start": 0, "end": 9, "username": "ArisDama", "id": "58855024"}]}, "lang": "pt", "in_reply_to_user_id": "58855024", "created_at": "2022-10-30T09:43:52.000Z", "edit_history_tweet_ids": ["1586655113799671809"], "conversation_id": "1586031604245606400", "author_id": "107472906", "public_metrics": {"retweet_count": 0, "reply_count": 0, "like_count": 0, "quote_count": 0}}, {"text": "@pazziniju @pazziniju Ol\u00e1, pode por favor indicar-nos o c\u00f3digo de reserva por forma a verificar?\nPor motivos de confidencialidade sugerimos o envio por mensagem direta. Obrigada.", "source": "Qualtrics Social Connect", "id": "1586629213792227328", "lang": "pt", "in_reply_to_user_id": "1481049606796492804", "created_at": "2022-10-30T08:00:57.000Z", "edit_history_tweet_ids": ["1586629213792227328"], "conversation_id": "1586333268504621057", "author_id": "107472906", "public_metrics": {"retweet_count": 0, "reply_count": 0, "like_count": 0, "quote_count": 0}, "entities": {"mentions": [{"start": 0, "end": 10, "username": "pazziniju", "id": "1481049606796492804"}, {"start": 11, "end": 21, "username": "pazziniju", "id": "1481049606796492804"}]}}, {"text": "@alexismbouchard Hello Alexis,\nwe have replied to your DM.\nThank you", "source": "Qualtrics Social Connect", "id": "1586628239262449665", "entities": {"annotations": [{"start": 23, "end": 28, "probability": 0.5355, "type": "Other", "normalized_text": "Alexis"}], "mentions": [{"start": 0, "end": 16, "username": "alexismbouchard", "id": "871030642728992768"}]}, "lang": "en", "in_reply_to_user_id": "871030642728992768", "created_at": "2022-10-30T07:57:05.000Z", "edit_history_tweet_ids": ["1586628239262449665"], "conversation_id": "1586314967082418177", "author_id": "107472906", "public_metrics": {"retweet_count": 0, "reply_count": 0, "like_count": 0, "quote_count": 0}}, {"text": "@vnmartins82 Ol\u00e1 V. Nuno Martins,\nCaso ainda possamos ajudar com alguma quest\u00e3o, por favor disponha.\nObrigado", "source": "Qualtrics Social Connect", "id": "1586624657549148160", "entities": {"annotations": [{"start": 20, "end": 31, "probability": 0.8206, "type": "Person", "normalized_text": "Nuno Martins"}], "mentions": [{"start": 0, "end": 12, "username": "vnmartins82", "id": "1096277084"}]}, "lang": "pt", "in_reply_to_user_id": "1096277084", "created_at": "2022-10-30T07:42:51.000Z", "edit_history_tweet_ids": ["1586624657549148160"], "conversation_id": "1586522943177527298", "author_id": "107472906", "public_metrics": {"retweet_count": 0, "reply_count": 1, "like_count": 0, "quote_count": 0}}, {"text": "@pfb15066134 Ol\u00e1 ped f bar,\nLamentamos esta situa\u00e7\u00e3o bem como todos os inconvenientes ocasionados pela mesma. Caso ainda possamos assisti-lo, por favor indique-nos o c\u00f3digo da sua reserva. Recomendamos que o fa\u00e7a por mensagem privada devido a raz\u00f5es de confidencialidade de dados.\nObrigado", "source": "Qualtrics Social Connect", "id": "1586624464522993664", "lang": "pt", "in_reply_to_user_id": "806917054750072834", "created_at": "2022-10-30T07:42:05.000Z", "edit_history_tweet_ids": ["1586624464522993664"], "conversation_id": "1586510221026873345", "author_id": "107472906", "public_metrics": {"retweet_count": 0, "reply_count": 0, "like_count": 0, "quote_count": 0}, "entities": {"mentions": [{"start": 0, "end": 12, "username": "pfb15066134", "id": "806917054750072834"}]}}, {"text": "@ebl4 Hello EBL4,\nwe have replied to your DM.\nThank you", "source": "Qualtrics Social Connect", "id": "1586623765965934595", "entities": {"annotations": [{"start": 12, "end": 15, "probability": 0.7909, "type": "Other", "normalized_text": "EBL4"}], "mentions": [{"start": 0, "end": 5, "username": "ebl4", "id": "304815788"}]}, "lang": "en", "in_reply_to_user_id": "304815788", "created_at": "2022-10-30T07:39:18.000Z", "edit_history_tweet_ids": ["1586623765965934595"], "conversation_id": "1586499601162702848", "author_id": "107472906", "public_metrics": {"retweet_count": 0, "reply_count": 0, "like_count": 0, "quote_count": 0}}, {"text": "@HerrGeissler Hello Christian,\n\ncan you inform us through DM your booking reference or electronic ticket number (047...) so we may verify? Thank you.", "source": "Qualtrics Social Connect", "id": "1586487799490179072", "entities": {"annotations": [{"start": 20, "end": 28, "probability": 0.6233, "type": "Person", "normalized_text": "Christian"}], "mentions": [{"start": 0, "end": 13, "username": "HerrGeissler", "id": "2781536709"}]}, "lang": "en", "in_reply_to_user_id": "2781536709", "created_at": "2022-10-29T22:39:01.000Z", "edit_history_tweet_ids": ["1586487799490179072"], "conversation_id": "1586486879519506432", "author_id": "107472906", "public_metrics": {"retweet_count": 0, "reply_count": 0, "like_count": 0, "quote_count": 0}}, {"text": "@Portos75 Ol\u00e1 Basilio,\n\nrefere-se a que voo, mais propriamente? Poderia clarificar, por favor?", "source": "Qualtrics Social Connect", "id": "1586481335035650048", "entities": {"annotations": [{"start": 14, "end": 20, "probability": 0.725, "type": "Person", "normalized_text": "Basilio"}], "mentions": [{"start": 0, "end": 9, "username": "Portos75", "id": "1103247528"}]}, "lang": "pt", "in_reply_to_user_id": "1103247528", "created_at": "2022-10-29T22:13:20.000Z", "edit_history_tweet_ids": ["1586481335035650048"], "conversation_id": "1586460845697290240", "author_id": "107472906", "public_metrics": {"retweet_count": 0, "reply_count": 0, "like_count": 0, "quote_count": 0}}, {"text": "@shay_muc Hello Miss Shay,\n\ncan you inform us through DM your lost luggage file number (PIR), bag tag and booking reference related so we may verify? Thank you.", "source": "Qualtrics Social Connect", "id": "1586475964833435648", "entities": {"annotations": [{"start": 21, "end": 24, "probability": 0.6292, "type": "Other", "normalized_text": "Shay"}], "mentions": [{"start": 0, "end": 9, "username": "shay_muc", "id": "395525375"}]}, "lang": "en", "in_reply_to_user_id": "395525375", "created_at": "2022-10-29T21:51:59.000Z", "edit_history_tweet_ids": ["1586475964833435648"], "conversation_id": "1586031604245606400", "author_id": "107472906", "public_metrics": {"retweet_count": 0, "reply_count": 0, "like_count": 0, "quote_count": 0}}, {"text": "@zahidahmedch Hello Zahid,\n\nWe sincerely apologize for the situation mentioned and the inconvenience caused. TAP Air Portugal works everyday in order to promote our passenger satisfaction and to improve our services. In case you require our assistance, please let us know. Thank yo", "source": "Qualtrics Social Connect", "id": "1586475302116540419", "entities": {"annotations": [{"start": 20, "end": 24, "probability": 0.5212, "type": "Person", "normalized_text": "Zahid"}, {"start": 109, "end": 111, "probability": 0.4546, "type": "Organization", "normalized_text": "TAP"}, {"start": 113, "end": 124, "probability": 0.3203, "type": "Organization", "normalized_text": "Air Portugal"}], "mentions": [{"start": 0, "end": 13, "username": "zahidahmedch", "id": "1541756924521324546"}]}, "lang": "en", "in_reply_to_user_id": "1541756924521324546", "created_at": "2022-10-29T21:49:21.000Z", "edit_history_tweet_ids": ["1586475302116540419"], "conversation_id": "1586469635859193856", "author_id": "107472906", "public_metrics": {"retweet_count": 1, "reply_count": 1, "like_count": 0, "quote_count": 1}}, {"text": "@amey_9879 Hello Amey, can you please provide us the booking reference? For security reasons, we suggest you do so by private message. Thank you.", "source": "Qualtrics Social Connect", "id": "1586475057626451973", "entities": {"annotations": [{"start": 17, "end": 20, "probability": 0.5641, "type": "Other", "normalized_text": "Amey"}], "mentions": [{"start": 0, "end": 10, "username": "amey_9879", "id": "2368380270"}]}, "lang": "en", "in_reply_to_user_id": "2368380270", "created_at": "2022-10-29T21:48:23.000Z", "edit_history_tweet_ids": ["1586475057626451973"], "conversation_id": "1586474484311040000", "author_id": "107472906", "public_metrics": {"retweet_count": 0, "reply_count": 0, "like_count": 0, "quote_count": 0}}, {"text": "@gmoxyz @WebSummit Hello, in order to verify, please provide us the booking reference and the e-ticket number. For confidentiality reasons, we suggest you to send the details by private message. Thank you.", "source": "Qualtrics Social Connect", "id": "1586431876545351685", "context_annotations": [{"domain": {"id": "29", "name": "Events [Entity Service]", "description": "Real world events. "}, "entity": {"id": "1579506648153878528", "name": "Web Summit 2022"}}, {"domain": {"id": "46", "name": "Business Taxonomy", "description": "Categories within Brand Verticals that narrow down the scope of Brands"}, "entity": {"id": "1557697333571112960", "name": "Technology Business", "description": "Brands, companies, advertisers and every non-person handle with the profit intent related to softwares, apps, communication equipments, hardwares"}}, {"domain": {"id": "131", "name": "Unified Twitter Taxonomy", "description": "A taxonomy of user interests. "}, "entity": {"id": "1303989823011606528", "name": "Tech events"}}, {"domain": {"id": "131", "name": "Unified Twitter Taxonomy", "description": "A taxonomy of user interests. "}, "entity": {"id": "1436053202835689485", "name": "Events"}}], "lang": "en", "in_reply_to_user_id": "42900273", "created_at": "2022-10-29T18:56:48.000Z", "edit_history_tweet_ids": ["1586431876545351685"], "conversation_id": "1586287717360766976", "author_id": "107472906", "public_metrics": {"retweet_count": 0, "reply_count": 0, "like_count": 0, "quote_count": 0}, "entities": {"mentions": [{"start": 0, "end": 7, "username": "gmoxyz", "id": "42900273"}, {"start": 8, "end": 18, "username": "WebSummit", "id": "74991835"}]}}, {"text": "@OrlandoFig Ol\u00e1 Orlando,\nlamentamos que a experi\u00eancia n\u00e3o tenha ido ao encontro das suas expectativas e por todo o constrangimento causado.\nCaso possamos ajudar com qualquer outra quest\u00e3o adicional, estamos ao dispor.", "source": "Qualtrics Social Connect", "id": "1586421811151081472", "entities": {"annotations": [{"start": 16, "end": 22, "probability": 0.5955, "type": "Place", "normalized_text": "Orlando"}], "mentions": [{"start": 0, "end": 11, "username": "OrlandoFig", "id": "14072078"}]}, "lang": "pt", "in_reply_to_user_id": "14072078", "created_at": "2022-10-29T18:16:48.000Z", "edit_history_tweet_ids": ["1586421811151081472"], "conversation_id": "1586283614194388992", "author_id": "107472906", "public_metrics": {"retweet_count": 0, "reply_count": 1, "like_count": 0, "quote_count": 0}}, {"text": "@dismarmar Hello notaname,\n\nin that case can you inform by DM us the following details so we may verify:\n\n- flight nonliterary, dates and schedule;\n-  passengers names and dates of birth;\n- email address and phone contact;\n- which fare do you wish to select (discount, classic, plus...).", "source": "Qualtrics Social Connect", "id": "1586417278781890565", "lang": "en", "in_reply_to_user_id": "17036440", "created_at": "2022-10-29T17:58:48.000Z", "edit_history_tweet_ids": ["1586417278781890565"], "conversation_id": "1586414521706496001", "author_id": "107472906", "public_metrics": {"retweet_count": 0, "reply_count": 0, "like_count": 0, "quote_count": 0}, "entities": {"mentions": [{"start": 0, "end": 10, "username": "dismarmar", "id": "17036440"}]}}, {"text": "@insideashes_ Hello Inside Ashes,\n\nhow may we assist you? Can you clarify your situation through DM so we may verify? Thank you.", "source": "Qualtrics Social Connect", "id": "1586412972523618306", "entities": {"annotations": [{"start": 20, "end": 31, "probability": 0.6783, "type": "Other", "normalized_text": "Inside Ashes"}], "mentions": [{"start": 0, "end": 13, "username": "insideashes_", "id": "1380868173801656321"}]}, "lang": "en", "in_reply_to_user_id": "1380868173801656321", "created_at": "2022-10-29T17:41:41.000Z", "edit_history_tweet_ids": ["1586412972523618306"], "conversation_id": "1586408201544617984", "author_id": "107472906", "public_metrics": {"retweet_count": 0, "reply_count": 1, "like_count": 0, "quote_count": 0}}, {"text": "@alcasber Hello Alberto,\n\ncan you inform us through DM your complaint file number and email address related so we may verify? Thank you.", "source": "Qualtrics Social Connect", "id": "1586388765739782144", "entities": {"annotations": [{"start": 16, "end": 22, "probability": 0.6027, "type": "Person", "normalized_text": "Alberto"}], "mentions": [{"start": 0, "end": 9, "username": "alcasber", "id": "50304068"}]}, "lang": "en", "in_reply_to_user_id": "50304068", "created_at": "2022-10-29T16:05:30.000Z", "edit_history_tweet_ids": ["1586388765739782144"], "conversation_id": "1586372997539328001", "author_id": "107472906", "public_metrics": {"retweet_count": 0, "reply_count": 0, "like_count": 0, "quote_count": 0}}, {"text": "@milvin01 Bonjour maric, une r\u00e9ponse vous a \u00e9t\u00e9 d\u00e9j\u00e0 apport\u00e9e via Facebook. Merci.", "source": "Qualtrics Social Connect", "id": "1586387212152836098", "context_annotations": [{"domain": {"id": "30", "name": "Entities [Entity Service]", "description": "Entity Service top level domain, every item that is in Entity Service should be in this domain"}, "entity": {"id": "781974596752842752", "name": "Services"}}, {"domain": {"id": "47", "name": "Brand", "description": "Brands and Companies"}, "entity": {"id": "10029202045", "name": "Facebook"}}, {"domain": {"id": "131", "name": "Unified Twitter Taxonomy", "description": "A taxonomy of user interests. "}, "entity": {"id": "10029202045", "name": "Facebook"}}, {"domain": {"id": "131", "name": "Unified Twitter Taxonomy", "description": "A taxonomy of user interests. "}, "entity": {"id": "1196446161223028736", "name": "Social media"}}, {"domain": {"id": "165", "name": "Technology", "description": "for individual and types of technology, e.g., food technology, 3D printing"}, "entity": {"id": "1196446161223028736", "name": "Social media"}}], "lang": "fr", "in_reply_to_user_id": "2798287602", "created_at": "2022-10-29T15:59:19.000Z", "edit_history_tweet_ids": ["1586387212152836098"], "conversation_id": "1586354831580889088", "author_id": "107472906", "public_metrics": {"retweet_count": 0, "reply_count": 0, "like_count": 0, "quote_count": 1}, "entities": {"mentions": [{"start": 0, "end": 9, "username": "milvin01", "id": "2798287602"}]}}, {"text": "@cannibaleyes96 Hello Cannibal,\n\nwe are sorry however we cannot predict when the complaint will be actually processed.", "source": "Qualtrics Social Connect", "id": "1586385497672253451", "entities": {"annotations": [{"start": 22, "end": 29, "probability": 0.4124, "type": "Other", "normalized_text": "Cannibal"}]}, "lang": "en", "in_reply_to_user_id": "442821644", "created_at": "2022-10-29T15:52:30.000Z", "edit_history_tweet_ids": ["1586385497672253451"], "conversation_id": "1586275502590816256", "author_id": "107472906", "public_metrics": {"retweet_count": 0, "reply_count": 1, "like_count": 0, "quote_count": 0}}, {"text": "@paul_audouy Hello Paulo, we have answered your private message. Thank you.", "source": "Qualtrics Social Connect", "id": "1586379036804145153", "entities": {"annotations": [{"start": 19, "end": 23, "probability": 0.6067, "type": "Person", "normalized_text": "Paulo"}], "mentions": [{"start": 0, "end": 12, "username": "paul_audouy", "id": "874000036450926592"}]}, "lang": "en", "in_reply_to_user_id": "874000036450926592", "created_at": "2022-10-29T15:26:50.000Z", "edit_history_tweet_ids": ["1586379036804145153"], "conversation_id": "1586031604245606400", "author_id": "107472906", "public_metrics": {"retweet_count": 0, "reply_count": 0, "like_count": 0, "quote_count": 0}}, {"text": "@drkafors Hello Karolina,\n\nhow may we assist you? Can you clarify your situation through DM so we mat verify? Thank you.", "source": "Qualtrics Social Connect", "id": "1586372602435600385", "entities": {"annotations": [{"start": 16, "end": 23, "probability": 0.5309, "type": "Person", "normalized_text": "Karolina"}], "mentions": [{"start": 0, "end": 9, "username": "drkafors", "id": "1485364046446616576"}]}, "lang": "en", "in_reply_to_user_id": "1485364046446616576", "created_at": "2022-10-29T15:01:16.000Z", "edit_history_tweet_ids": ["1586372602435600385"], "conversation_id": "1586329995072315393", "author_id": "107472906", "public_metrics": {"retweet_count": 0, "reply_count": 0, "like_count": 0, "quote_count": 0}}, {"text": "@smileykopf Hello Jaki,\nwe have replied to your DM.\nThank you", "source": "Qualtrics Social Connect", "id": "1586369254462570503", "entities": {"annotations": [{"start": 18, "end": 21, "probability": 0.6231, "type": "Other", "normalized_text": "Jaki"}], "mentions": [{"start": 0, "end": 11, "username": "smileykopf", "id": "263160807"}]}, "lang": "en", "in_reply_to_user_id": "263160807", "created_at": "2022-10-29T14:47:58.000Z", "edit_history_tweet_ids": ["1586369254462570503"], "conversation_id": "1586348477960769536", "author_id": "107472906", "public_metrics": {"retweet_count": 0, "reply_count": 0, "like_count": 0, "quote_count": 0}}, {"text": "@macgodlewski Hello Matthias,\nWe answered per DM.", "source": "Qualtrics Social Connect", "id": "1586367155179847683", "entities": {"annotations": [{"start": 20, "end": 27, "probability": 0.7186, "type": "Person", "normalized_text": "Matthias"}], "mentions": [{"start": 0, "end": 13, "username": "macgodlewski", "id": "2356901922"}]}, "lang": "en", "in_reply_to_user_id": "2356901922", "created_at": "2022-10-29T14:39:37.000Z", "edit_history_tweet_ids": ["1586367155179847683"], "conversation_id": "1585574625072889857", "author_id": "107472906", "public_metrics": {"retweet_count": 0, "reply_count": 0, "like_count": 0, "quote_count": 0}}, {"text": "@Giridja Hello Olesia,\nSince you have already submitted your complaint, your case will be analyzed and you will be contacted by email once this analysis is complete.\nThank you", "source": "Qualtrics Social Connect", "id": "1586361617830346755", "entities": {"annotations": [{"start": 15, "end": 20, "probability": 0.5418, "type": "Other", "normalized_text": "Olesia"}], "mentions": [{"start": 0, "end": 8, "username": "Giridja", "id": "2408923879"}]}, "lang": "en", "in_reply_to_user_id": "2408923879", "created_at": "2022-10-29T14:17:37.000Z", "edit_history_tweet_ids": ["1586361617830346755"], "conversation_id": "1585574637370593285", "author_id": "107472906", "public_metrics": {"retweet_count": 0, "reply_count": 0, "like_count": 0, "quote_count": 0}}, {"text": "@IsaCNN We have replied again through private message, Isa. Thank you.", "source": "Qualtrics Social Connect", "id": "1586359137541267457", "entities": {"annotations": [{"start": 55, "end": 57, "probability": 0.8058, "type": "Other", "normalized_text": "Isa"}], "mentions": [{"start": 0, "end": 7, "username": "IsaCNN", "id": "388388260"}]}, "lang": "en", "in_reply_to_user_id": "388388260", "created_at": "2022-10-29T14:07:46.000Z", "edit_history_tweet_ids": ["1586359137541267457"], "conversation_id": "1586339669654253570", "author_id": "107472906", "public_metrics": {"retweet_count": 0, "reply_count": 0, "like_count": 0, "quote_count": 0}}], "includes": {"users": [{"id": "32544131", "name": "Nicole Humphreys", "username": "Nicole_H31"}, {"id": "64900929", "name": "Vanessa Salles", "username": "vsalles_"}, {"id": "1423990612802609159", "name": "Nicole", "username": "NikkiChagra"}, {"id": "1236791282929991681", "name": "Legumendoas \ud83c\udf31", "username": "Legumendoas"}, {"id": "1468451477392076806", "name": "Diego Cedraz", "username": "cedraz_diego"}, {"id": "1449854727920013319", "name": "Ellesmama", "username": "Ellesmama1"}, {"id": "1572346755999571971", "name": "acruzarelcharco", "username": "acruzarelcharco"}, {"id": "94226444", "name": "N\u00e1utico NauticoNET", "username": "NauticoNET1998"}, {"id": "215653906", "name": "Sanine Moreira \u26aa\ufe0f", "username": "saninemoreira"}, {"id": "729907646577381376", "name": "Heather", "username": "HevMM01"}, {"id": "2824792399", "name": "Kach Umandap", "username": "2MonkeysTravel"}, {"id": "3096799408", "name": "Dr. Ronit yarden", "username": "Run_itt"}, {"id": "252246576", "name": "Diego Jatem", "username": "diegojatem"}, {"id": "27067896", "name": "IATA", "username": "IATA"}, {"id": "58855024", "name": "Aris Dama", "username": "ArisDama"}, {"id": "1425360932386054146", "name": "Roy McCaw", "username": "roy_mccaw"}, {"id": "791736167213432832", "name": "Giuseppe", "username": "GiuseppePeltron"}, {"id": "80430427", "name": "Emily Tamfo", "username": "emtamfabulous"}, {"id": "125065841", "name": "Wasim", "username": "Wasim571"}, {"id": "2821628915", "name": "morgan costa", "username": "mocosta3"}, {"id": "131241408", "name": "Leo", "username": "la_taupe123"}, {"id": "68679960", "name": "TAP Portugal", "username": "TAP_Portugal"}, {"id": "59655069", "name": "Mike O'Sullivan", "username": "mikesyard"}, {"id": "1141634260744454144", "name": "L\u00c9GER Nicolas", "username": "Nicolas1Leger"}, {"id": "194049699", "name": "RAJESH SONI", "username": "rajeshkal123"}, {"id": "214980160", "name": "Jaume Risquete S\u00e1nchez", "username": "risquete"}, {"id": "12275822", "name": "DivaNotADivaDuMonde", "username": "ndfeed"}, {"id": "58467662", "name": "SC", "username": "iamstevecook"}, {"id": "890480767", "name": "Pia Berglund", "username": "Attilapia"}, {"id": "1447425996", "name": "morgan", "username": "rosebella2121"}, {"id": "39305481", "name": "Terrence", "username": "TerrenzVM"}, {"id": "1480167472741421058", "name": "Elina Asikainen", "username": "AsikainenElina"}, {"id": "57639281", "name": "Angelique Pouponneau", "username": "ANGIEPOPS11"}, {"id": "987907015287672832", "name": "BlackWomanCorp", "username": "Shon70399056"}, {"id": "1586605321950269440", "name": "myswetheart", "username": "forrwithmycat"}, {"id": "940336346819973122", "name": "Sandra Carvalho", "username": "Smvmc89"}, {"id": "1229125723371266048", "name": "Karry Melchiades", "username": "KarryMelchiades"}, {"id": "1581262025493192704", "name": "Tales Lisboa", "username": "TalesLisboa2"}, {"id": "856920506", "name": "Pratik K", "username": "Dynamo17Pratik"}, {"id": "1586779081852555264", "name": "Mike Croonenborghs", "username": "MikeCroon"}, {"id": "52180053", "name": "Iuri Farenzena", "username": "iurifarenzena"}, {"id": "26698036", "name": "Rodrigo Salgado", "username": "Rodrig0Salgado"}, {"id": "826834231", "name": "Utkarsh Kumar", "username": "utpandey"}, {"id": "981277278612180992", "name": "Elizabeth Sheppard Sellam", "username": "DrLiz16"}, {"id": "422895602", "name": "Nuno Baptista", "username": "Prof_Baptista"}, {"id": "1447508709555507209", "name": "Marion Adeline", "username": "Marion_Adln"}, {"id": "311728138", "name": "MJRunner", "username": "MJOneDone"}, {"id": "478501702", "name": "Marie Gu\u00e9rin", "username": "Guerin_Marie"}, {"id": "3390775469", "name": "TF1Info", "username": "TF1Info"}, {"id": "26110930", "name": "LCI", "username": "LCI"}, {"id": "34294667", "name": "RTL France", "username": "RTLFrance"}, {"id": "34570323", "name": "Europe 1 \ud83c\udfa7\ud83c\udf0d\ud83d\udcfb", "username": "Europe1"}, {"id": "828931483", "name": "Julien Courbet", "username": "courbet_julien"}, {"id": "67011819", "name": "Johan Muijres", "username": "JohanMuijres"}, {"id": "1543721616", "name": "Eddie", "username": "EddieLee42"}, {"id": "1583158278871449600", "name": "yu", "username": "yu26440222"}, {"id": "588571606", "name": "Miguel Melero", "username": "Manchestnero"}, {"id": "3417520654", "name": "Benedetta Dal Canton", "username": "benedetta_dc"}, {"id": "1000066766033358849", "name": "BertrandStefani", "username": "StefaniBertrand"}, {"id": "415594401", "name": "DGCCRF", "username": "dgccrf"}, {"id": "224140014", "name": "Direction g\u00e9n\u00e9rale de l'aviation civile \ud83c\uddeb\ud83c\uddf7\ud83c\uddea\ud83c\uddfa", "username": "DGAC"}, {"id": "21924681", "name": "Suri", "username": "SuriR"}, {"id": "59471800", "name": "Nicol\u00f2 Santambrogio", "username": "Santambreus"}, {"id": "991683256360886273", "name": "Italy in Portugal", "username": "ItalyinPortugal"}, {"id": "19903099", "name": "Turismo de Portugal", "username": "turismoportugal"}, {"id": "395388847", "name": "Di\u00e1rio de Not\u00edcias", "username": "dntwit"}, {"id": "68130004", "name": "Hannah McMellon", "username": "hannahmc38"}, {"id": "3300502500", "name": "Siddant \ud83c\udf6d", "username": "injuredcheetah"}, {"id": "395525375", "name": "Miss Shay", "username": "shay_muc"}, {"id": "2324101719", "name": "Kevin", "username": "c1othes11"}, {"id": "1481049606796492804", "name": "Julia Truques", "username": "pazziniju"}, {"id": "871030642728992768", "name": "Alexis Bouchard", "username": "alexismbouchard"}, {"id": "1096277084", "name": "V. Nuno Martins \ud83c\uddfa\ud83c\udde6", "username": "vnmartins82"}, {"id": "806917054750072834", "name": "ped f bar", "username": "pfb15066134"}, {"id": "304815788", "name": "EBL4", "username": "ebl4"}, {"id": "2781536709", "name": "Christian Geissler", "username": "HerrGeissler"}, {"id": "1103247528", "name": "Basilio Simoes", "username": "Portos75"}, {"id": "1541756924521324546", "name": "zahid ahmed", "username": "zahidahmedch"}, {"id": "2368380270", "name": "Amey Bandodkar", "username": "amey_9879"}, {"id": "42900273", "name": "gmoxyz.eth", "username": "gmoxyz"}, {"id": "74991835", "name": "Web Summit", "username": "WebSummit"}, {"id": "17036440", "name": "notaname", "username": "dismarmar"}, {"id": "1380868173801656321", "name": "insideashes\ud83c\uddfa\ud83c\udde6\ud83c\udf97", "username": "insideashes_"}, {"id": "50304068", "name": "Alberto Casillas", "username": "alcasber"}, {"id": "2798287602", "name": "maric", "username": "milvin01"}, {"id": "874000036450926592", "name": "Paulo", "username": "paul_audouy"}, {"id": "1485364046446616576", "name": "Karolina Afors", "username": "drkafors"}, {"id": "263160807", "name": "Jaki", "username": "smileykopf"}, {"id": "2356901922", "name": "Matthias Godlevsky", "username": "macgodlewski"}, {"id": "2408923879", "name": "\ud83d\udc1d Olesia Korobka \ud83d\udc99\ud83d\udc9b\ud83d\udc1d", "username": "Giridja"}, {"id": "388388260", "name": "Isa Soares", "username": "IsaCNN"}]}, "errors": [{"resource_id": "alicolas22", "parameter": "entities.mentions.username", "resource_type": "user", "section": "includes", "title": "Authorization Error", "value": "alicolas22", "detail": "Sorry, you are not authorized to see the user with entities.mentions.username: [alicolas22].", "type": "https://api.twitter.com/2/problems/not-authorized-for-resource"}, {"value": "OrlandoFig", "detail": "Could not find user with entities.mentions.username: [OrlandoFig].", "title": "Not Found Error", "resource_type": "user", "parameter": "entities.mentions.username", "resource_id": "OrlandoFig", "type": "https://api.twitter.com/2/problems/resource-not-found"}], "meta": {"next_token": "7140dibdnow9c7btw423x54ubgmhli4gl95qg84wglmif", "result_count": 100, "newest_id": "1587111368381054976", "oldest_id": "1586359137541267457", "previous_token": "77qpymm88g5h9vqklurfdmrbgts1ty3w82powqfynj0ae"}}